Workbook

Sheet Weekly Report
B2: Weekly Sales Report
B3: ="Week starting "&TEXT('Weekly Calc'!$H$3,"d mmmm yyyy")&" · rebuilt automatically from the Raw Orders tab" -> Week starting 3 August 2026 · rebuilt automatically from the Raw Orders tab
B5: REVENUE | D5: ORDERS | F5: AVG ORDER VALUE | H5: UNITS SOLD | J5: VS LAST WEEK
B6: =INDEX('Weekly Calc'!$I$5:$I$20,MATCH('Weekly Calc'!$H$3,'Weekly Calc'!$H$5:$H$20,0)) -> 6840.05 | D6: =INDEX('Weekly Calc'!$J$5:$J$20,MATCH('Weekly Calc'!$H$3,'Weekly Calc'!$H$5:$H$20,0)) -> 63 | F6: =INDEX('Weekly Calc'!$M$5:$M$20,MATCH('Weekly Calc'!$H$3,'Weekly Calc'!$H$5:$H$20,0)) -> 108.57222 | H6: =INDEX('Weekly Calc'!$K$5:$K$20,MATCH('Weekly Calc'!$H$3,'Weekly Calc'!$H$5:$H$20,0)) -> 149 | J6: =INDEX('Weekly Calc'!$N$5:$N$20,MATCH('Weekly Calc'!$H$3,'Weekly Calc'!$H$5:$H$20,0)) -> 0.31234052
B7: fulfilled product lines | D7: distinct orders | F7: revenue divided by orders | H7: items shipped | J7: change in revenue
B9: Revenue counts fulfilled product lines only. Shipping, discounts, cancellations and refunds are excluded and reported separately at the bottom, so this figure reconciles to the raw export.
B11: Revenue, last 14 weeks
B12: Week starting | C12: Revenue | D12: Orders | E12: Avg order value | F12: vs prior week
B13: =('Weekly Calc'!$H$3-91) -> 46146 | C13: =IFERROR(INDEX('Weekly Calc'!$I$5:$I$20,MATCH(('Weekly Calc'!$H$3-91),'Weekly Calc'!$H$5:$H$20,0)),0) -> 6169.5 | D13: =IFERROR(INDEX('Weekly Calc'!$J$5:$J$20,MATCH(('Weekly Calc'!$H$3-91),'Weekly Calc'!$H$5:$H$20,0)),0) -> 56 | E13: =IFERROR(INDEX('Weekly Calc'!$M$5:$M$20,MATCH(('Weekly Calc'!$H$3-91),'Weekly Calc'!$H$5:$H$20,0)),0) -> 110.16964 | F13: =IFERROR(IF(INDEX('Weekly Calc'!$N$5:$N$20,MATCH(('Weekly Calc'!$H$3-91),'Weekly Calc'!$H$5:$H$20,0))="","",INDEX('Weekly Calc'!$N$5:$N$20,MATCH(('Weekly Calc'!$H$3-91),'Weekly Calc'!$H$5:$H$20,0))),"")
B14: =('Weekly Calc'!$H$3-84) -> 46153 | C14: =IFERROR(INDEX('Weekly Calc'!$I$5:$I$20,MATCH(('Weekly Calc'!$H$3-84),'Weekly Calc'!$H$5:$H$20,0)),0) -> 4203.05 | D14: =IFERROR(INDEX('Weekly Calc'!$J$5:$J$20,MATCH(('Weekly Calc'!$H$3-84),'Weekly Calc'!$H$5:$H$20,0)),0) -> 44 | E14: =IFERROR(INDEX('Weekly Calc'!$M$5:$M$20,MATCH(('Weekly Calc'!$H$3-84),'Weekly Calc'!$H$5:$H$20,0)),0) -> 95.523864 | F14: =IFERROR(IF(INDEX('Weekly Calc'!$N$5:$N$20,MATCH(('Weekly Calc'!$H$3-84),'Weekly Calc'!$H$5:$H$20,0))="","",INDEX('Weekly Calc'!$N$5:$N$20,MATCH(('Weekly Calc'!$H$3-84),'Weekly Calc'!$H$5:$H$20,0))),"") -> -0.31873734
B15: =('Weekly Calc'!$H$3-77) -> 46160 | C15: =IFERROR(INDEX('Weekly Calc'!$I$5:$I$20,MATCH(('Weekly Calc'!$H$3-77),'Weekly Calc'!$H$5:$H$20,0)),0) -> 3420.3 | D15: =IFERROR(INDEX('Weekly Calc'!$J$5:$J$20,MATCH(('Weekly Calc'!$H$3-77),'Weekly Calc'!$H$5:$H$20,0)),0) -> 38 | E15: =IFERROR(INDEX('Weekly Calc'!$M$5:$M$20,MATCH(('Weekly Calc'!$H$3-77),'Weekly Calc'!$H$5:$H$20,0)),0) -> 90.007895 | F15: =IFERROR(IF(INDEX('Weekly Calc'!$N$5:$N$20,MATCH(('Weekly Calc'!$H$3-77),'Weekly Calc'!$H$5:$H$20,0))="","",INDEX('Weekly Calc'!$N$5:$N$20,MATCH(('Weekly Calc'!$H$3-77),'Weekly Calc'!$H$5:$H$20,0))),"") -> -0.18623381
B16: =('Weekly Calc'!$H$3-70) -> 46167 | C16: =IFERROR(INDEX('Weekly Calc'!$I$5:$I$20,MATCH(('Weekly Calc'!$H$3-70),'Weekly Calc'!$H$5:$H$20,0)),0) -> 5843.8 | D16: =IFERROR(INDEX('Weekly Calc'!$J$5:$J$20,MATCH(('Weekly Calc'!$H$3-70),'Weekly Calc'!$H$5:$H$20,0)),0) -> 53 | E16: =IFERROR(INDEX('Weekly Calc'!$M$5:$M$20,MATCH(('Weekly Calc'!$H$3-70),'Weekly Calc'!$H$5:$H$20,0)),0) -> 110.26038 | F16: =IFERROR(IF(INDEX('Weekly Calc'!$N$5:$N$20,MATCH(('Weekly Calc'!$H$3-70),'Weekly Calc'!$H$5:$H$20,0))="","",INDEX('Weekly Calc'!$N$5:$N$20,MATCH(('Weekly Calc'!$H$3-70),'Weekly Calc'!$H$5:$H$20,0))),"") -> 0.70856358
B17: =('Weekly Calc'!$H$3-63) -> 46174 | C17: =IFERROR(INDEX('Weekly Calc'!$I$5:$I$20,MATCH(('Weekly Calc'!$H$3-63),'Weekly Calc'!$H$5:$H$20,0)),0) -> 4768 | D17: =IFERROR(INDEX('Weekly Calc'!$J$5:$J$20,MATCH(('Weekly Calc'!$H$3-63),'Weekly Calc'!$H$5:$H$20,0)),0) -> 58 | E17: =IFERROR(INDEX('Weekly Calc'!$M$5:$M$20,MATCH(('Weekly Calc'!$H$3-63),'Weekly Calc'!$H$5:$H$20,0)),0) -> 82.206897 | F17: =IFERROR(IF(INDEX('Weekly Calc'!$N$5:$N$20,MATCH(('Weekly Calc'!$H$3-63),'Weekly Calc'!$H$5:$H$20,0))="","",INDEX('Weekly Calc'!$N$5:$N$20,MATCH(('Weekly Calc'!$H$3-63),'Weekly Calc'!$H$5:$H$20,0))),"") -> -0.18409254
B18: =('Weekly Calc'!$H$3-56) -> 46181 | C18: =IFERROR(INDEX('Weekly Calc'!$I$5:$I$20,MATCH(('Weekly Calc'!$H$3-56),'Weekly Calc'!$H$5:$H$20,0)),0) -> 4908.2 | D18: =IFERROR(INDEX('Weekly Calc'!$J$5:$J$20,MATCH(('Weekly Calc'!$H$3-56),'Weekly Calc'!$H$5:$H$20,0)),0) -> 54 | E18: =IFERROR(INDEX('Weekly Calc'!$M$5:$M$20,MATCH(('Weekly Calc'!$H$3-56),'Weekly Calc'!$H$5:$H$20,0)),0) -> 90.892593 | F18: =IFERROR(IF(INDEX('Weekly Calc'!$N$5:$N$20,MATCH(('Weekly Calc'!$H$3-56),'Weekly Calc'!$H$5:$H$20,0))="","",INDEX('Weekly Calc'!$N$5:$N$20,MATCH(('Weekly Calc'!$H$3-56),'Weekly Calc'!$H$5:$H$20,0))),"") -> 0.029404362
B19: =('Weekly Calc'!$H$3-49) -> 46188 | C19: =IFERROR(INDEX('Weekly Calc'!$I$5:$I$20,MATCH(('Weekly Calc'!$H$3-49),'Weekly Calc'!$H$5:$H$20,0)),0) -> 5063 | D19: =IFERROR(INDEX('Weekly Calc'!$J$5:$J$20,MATCH(('Weekly Calc'!$H$3-49),'Weekly Calc'!$H$5:$H$20,0)),0) -> 52 | E19: =IFERROR(INDEX('Weekly Calc'!$M$5:$M$20,MATCH(('Weekly Calc'!$H$3-49),'Weekly Calc'!$H$5:$H$20,0)),0) -> 97.365385 | F19: =IFERROR(IF(INDEX('Weekly Calc'!$N$5:$N$20,MATCH(('Weekly Calc'!$H$3-49),'Weekly Calc'!$H$5:$H$20,0))="","",INDEX('Weekly Calc'!$N$5:$N$20,MATCH(('Weekly Calc'!$H$3-49),'Weekly Calc'!$H$5:$H$20,0))),"") -> 0.031539057
B20: =('Weekly Calc'!$H$3-42) -> 46195 | C20: =IFERROR(INDEX('Weekly Calc'!$I$5:$I$20,MATCH(('Weekly Calc'!$H$3-42),'Weekly Calc'!$H$5:$H$20,0)),0) -> 4877.55 | D20: =IFERROR(INDEX('Weekly Calc'!$J$5:$J$20,MATCH(('Weekly Calc'!$H$3-42),'Weekly Calc'!$H$5:$H$20,0)),0) -> 50 | E20: =IFERROR(INDEX('Weekly Calc'!$M$5:$M$20,MATCH(('Weekly Calc'!$H$3-42),'Weekly Calc'!$H$5:$H$20,0)),0) -> 97.551 | F20: =IFERROR(IF(INDEX('Weekly Calc'!$N$5:$N$20,MATCH(('Weekly Calc'!$H$3-42),'Weekly Calc'!$H$5:$H$20,0))="","",INDEX('Weekly Calc'!$N$5:$N$20,MATCH(('Weekly Calc'!$H$3-42),'Weekly Calc'!$H$5:$H$20,0))),"") -> -0.036628481
B21: =('Weekly Calc'!$H$3-35) -> 46202 | C21: =IFERROR(INDEX('Weekly Calc'!$I$5:$I$20,MATCH(('Weekly Calc'!$H$3-35),'Weekly Calc'!$H$5:$H$20,0)),0) -> 5541.3 | D21: =IFERROR(INDEX('Weekly Calc'!$J$5:$J$20,MATCH(('Weekly Calc'!$H$3-35),'Weekly Calc'!$H$5:$H$20,0)),0) -> 55 | E21: =IFERROR(INDEX('Weekly Calc'!$M$5:$M$20,MATCH(('Weekly Calc'!$H$3-35),'Weekly Calc'!$H$5:$H$20,0)),0) -> 100.75091 | F21: =IFERROR(IF(INDEX('Weekly Calc'!$N$5:$N$20,MATCH(('Weekly Calc'!$H$3-35),'Weekly Calc'!$H$5:$H$20,0))="","",INDEX('Weekly Calc'!$N$5:$N$20,MATCH(('Weekly Calc'!$H$3-35),'Weekly Calc'!$H$5:$H$20,0))),"") -> 0.13608266
B22: =('Weekly Calc'!$H$3-28) -> 46209 | C22: =IFERROR(INDEX('Weekly Calc'!$I$5:$I$20,MATCH(('Weekly Calc'!$H$3-28),'Weekly Calc'!$H$5:$H$20,0)),0) -> 5333.1 | D22: =IFERROR(INDEX('Weekly Calc'!$J$5:$J$20,MATCH(('Weekly Calc'!$H$3-28),'Weekly Calc'!$H$5:$H$20,0)),0) -> 46 | E22: =IFERROR(INDEX('Weekly Calc'!$M$5:$M$20,MATCH(('Weekly Calc'!$H$3-28),'Weekly Calc'!$H$5:$H$20,0)),0) -> 115.93696 | F22: =IFERROR(IF(INDEX('Weekly Calc'!$N$5:$N$20,MATCH(('Weekly Calc'!$H$3-28),'Weekly Calc'!$H$5:$H$20,0))="","",INDEX('Weekly Calc'!$N$5:$N$20,MATCH(('Weekly Calc'!$H$3-28),'Weekly Calc'!$H$5:$H$20,0))),"") -> -0.037572411
B23: =('Weekly Calc'!$H$3-21) -> 46216 | C23: =IFERROR(INDEX('Weekly Calc'!$I$5:$I$20,MATCH(('Weekly Calc'!$H$3-21),'Weekly Calc'!$H$5:$H$20,0)),0) -> 5796.8 | D23: =IFERROR(INDEX('Weekly Calc'!$J$5:$J$20,MATCH(('Weekly Calc'!$H$3-21),'Weekly Calc'!$H$5:$H$20,0)),0) -> 54 | E23: =IFERROR(INDEX('Weekly Calc'!$M$5:$M$20,MATCH(('Weekly Calc'!$H$3-21),'Weekly Calc'!$H$5:$H$20,0)),0) -> 107.34815 | F23: =IFERROR(IF(INDEX('Weekly Calc'!$N$5:$N$20,MATCH(('Weekly Calc'!$H$3-21),'Weekly Calc'!$H$5:$H$20,0))="","",INDEX('Weekly Calc'!$N$5:$N$20,MATCH(('Weekly Calc'!$H$3-21),'Weekly Calc'!$H$5:$H$20,0))),"") -> 0.086947554
B24: =('Weekly Calc'!$H$3-14) -> 46223 | C24: =IFERROR(INDEX('Weekly Calc'!$I$5:$I$20,MATCH(('Weekly Calc'!$H$3-14),'Weekly Calc'!$H$5:$H$20,0)),0) -> 3991.3 | D24: =IFERROR(INDEX('Weekly Calc'!$J$5:$J$20,MATCH(('Weekly Calc'!$H$3-14),'Weekly Calc'!$H$5:$H$20,0)),0) -> 46 | E24: =IFERROR(INDEX('Weekly Calc'!$M$5:$M$20,MATCH(('Weekly Calc'!$H$3-14),'Weekly Calc'!$H$5:$H$20,0)),0) -> 86.767391 | F24: =IFERROR(IF(INDEX('Weekly Calc'!$N$5:$N$20,MATCH(('Weekly Calc'!$H$3-14),'Weekly Calc'!$H$5:$H$20,0))="","",INDEX('Weekly Calc'!$N$5:$N$20,MATCH(('Weekly Calc'!$H$3-14),'Weekly Calc'!$H$5:$H$20,0))),"") -> -0.31146495
B25: =('Weekly Calc'!$H$3-7) -> 46230 | C25: =IFERROR(INDEX('Weekly Calc'!$I$5:$I$20,MATCH(('Weekly Calc'!$H$3-7),'Weekly Calc'!$H$5:$H$20,0)),0) -> 5212.1 | D25: =IFERROR(INDEX('Weekly Calc'!$J$5:$J$20,MATCH(('Weekly Calc'!$H$3-7),'Weekly Calc'!$H$5:$H$20,0)),0) -> 48 | E25: =IFERROR(INDEX('Weekly Calc'!$M$5:$M$20,MATCH(('Weekly Calc'!$H$3-7),'Weekly Calc'!$H$5:$H$20,0)),0) -> 108.58542 | F25: =IFERROR(IF(INDEX('Weekly Calc'!$N$5:$N$20,MATCH(('Weekly Calc'!$H$3-7),'Weekly Calc'!$H$5:$H$20,0))="","",INDEX('Weekly Calc'!$N$5:$N$20,MATCH(('Weekly Calc'!$H$3-7),'Weekly Calc'!$H$5:$H$20,0))),"") -> 0.30586526
B26: =('Weekly Calc'!$H$3-0) -> 46237 | C26: =IFERROR(INDEX('Weekly Calc'!$I$5:$I$20,MATCH(('Weekly Calc'!$H$3-0),'Weekly Calc'!$H$5:$H$20,0)),0) -> 6840.05 | D26: =IFERROR(INDEX('Weekly Calc'!$J$5:$J$20,MATCH(('Weekly Calc'!$H$3-0),'Weekly Calc'!$H$5:$H$20,0)),0) -> 63 | E26: =IFERROR(INDEX('Weekly Calc'!$M$5:$M$20,MATCH(('Weekly Calc'!$H$3-0),'Weekly Calc'!$H$5:$H$20,0)),0) -> 108.57222 | F26: =IFERROR(IF(INDEX('Weekly Calc'!$N$5:$N$20,MATCH(('Weekly Calc'!$H$3-0),'Weekly Calc'!$H$5:$H$20,0))="","",INDEX('Weekly Calc'!$N$5:$N$20,MATCH(('Weekly Calc'!$H$3-0),'Weekly Calc'!$H$5:$H$20,0))),"") -> 0.31234052
B28: Top products this week | F28: Revenue by channel
B29: Product | C29: Revenue | D29: Units | F29: Channel | G29: Revenue | H29: Share
B30: =IFERROR(INDEX('Weekly Calc'!$P$5:$P$15,MATCH(LARGE('Weekly Calc'!$Q$5:$Q$15,1),'Weekly Calc'!$Q$5:$Q$15,0)),"") -> Linen Bedding Set | C30: =IFERROR(LARGE('Weekly Calc'!$Q$5:$Q$15,1),"") -> 2006.95 | D30: =IFERROR(INDEX('Weekly Calc'!$R$5:$R$15,MATCH(LARGE('Weekly Calc'!$Q$5:$Q$15,1),'Weekly Calc'!$Q$5:$Q$15,0)),"") -> 24 | F30: ='Weekly Calc'!T5 -> Amazon | G30: ='Weekly Calc'!U5 -> 779.15 | H30: =IFERROR(G30/SUM($G$30:$G$34),0) -> 0.11390999
B31: =IFERROR(INDEX('Weekly Calc'!$P$5:$P$15,MATCH(LARGE('Weekly Calc'!$Q$5:$Q$15,2),'Weekly Calc'!$Q$5:$Q$15,0)),"") -> Weighted Blanket 7kg | C31: =IFERROR(LARGE('Weekly Calc'!$Q$5:$Q$15,2),"") -> 1587 | D31: =IFERROR(INDEX('Weekly Calc'!$R$5:$R$15,MATCH(LARGE('Weekly Calc'!$Q$5:$Q$15,2),'Weekly Calc'!$Q$5:$Q$15,0)),"") -> 24 | F31: ='Weekly Calc'!T6 -> Etsy | G31: ='Weekly Calc'!U6 -> 418 | H31: =IFERROR(G31/SUM($G$30:$G$34),0) -> 0.061110664
B32: =IFERROR(INDEX('Weekly Calc'!$P$5:$P$15,MATCH(LARGE('Weekly Calc'!$Q$5:$Q$15,3),'Weekly Calc'!$Q$5:$Q$15,0)),"") -> Bamboo Pillow Pair | C32: =IFERROR(LARGE('Weekly Calc'!$Q$5:$Q$15,3),"") -> 702 | D32: =IFERROR(INDEX('Weekly Calc'!$R$5:$R$15,MATCH(LARGE('Weekly Calc'!$Q$5:$Q$15,3),'Weekly Calc'!$Q$5:$Q$15,0)),"") -> 20 | F32: ='Weekly Calc'!T7 -> Instagram | G32: ='Weekly Calc'!U7 -> 1169.1 | H32: =IFERROR(G32/SUM($G$30:$G$34),0) -> 0.1709198
B33: =IFERROR(INDEX('Weekly Calc'!$P$5:$P$15,MATCH(LARGE('Weekly Calc'!$Q$5:$Q$15,4),'Weekly Calc'!$Q$5:$Q$15,0)),"") -> Mattress Protector | C33: =IFERROR(LARGE('Weekly Calc'!$Q$5:$Q$15,4),"") -> 619.5 | D33: =IFERROR(INDEX('Weekly Calc'!$R$5:$R$15,MATCH(LARGE('Weekly Calc'!$Q$5:$Q$15,4),'Weekly Calc'!$Q$5:$Q$15,0)),"") -> 19 | F33: ='Weekly Calc'!T8 -> Website | G33: ='Weekly Calc'!U8 -> 4201.9 | H33: =IFERROR(G33/SUM($G$30:$G$34),0) -> 0.61430837
B34: =IFERROR(INDEX('Weekly Calc'!$P$5:$P$15,MATCH(LARGE('Weekly Calc'!$Q$5:$Q$15,5),'Weekly Calc'!$Q$5:$Q$15,0)),"") -> Cotton Waffle Throw | C34: =IFERROR(LARGE('Weekly Calc'!$Q$5:$Q$15,5),"") -> 585 | D34: =IFERROR(INDEX('Weekly Calc'!$R$5:$R$15,MATCH(LARGE('Weekly Calc'!$Q$5:$Q$15,5),'Weekly Calc'!$Q$5:$Q$15,0)),"") -> 14 | F34: ='Weekly Calc'!T9 -> Wholesale | G34: ='Weekly Calc'!U9 -> 271.9 | H34: =IFERROR(G34/SUM($G$30:$G$34),0) -> 0.039751171
B35: =IFERROR(INDEX('Weekly Calc'!$P$5:$P$15,MATCH(LARGE('Weekly Calc'!$Q$5:$Q$15,6),'Weekly Calc'!$Q$5:$Q$15,0)),"") -> Fitted Sheet Single | C35: =IFERROR(LARGE('Weekly Calc'!$Q$5:$Q$15,6),"") -> 326.7 | D35: =IFERROR(INDEX('Weekly Calc'!$R$5:$R$15,MATCH(LARGE('Weekly Calc'!$Q$5:$Q$15,6),'Weekly Calc'!$Q$5:$Q$15,0)),"") -> 17
B36: =IFERROR(INDEX('Weekly Calc'!$P$5:$P$15,MATCH(LARGE('Weekly Calc'!$Q$5:$Q$15,7),'Weekly Calc'!$Q$5:$Q$15,0)),"") -> Duvet Inner 10.5 tog | C36: =IFERROR(LARGE('Weekly Calc'!$Q$5:$Q$15,7),"") -> 300 | D36: =IFERROR(INDEX('Weekly Calc'!$R$5:$R$15,MATCH(LARGE('Weekly Calc'!$Q$5:$Q$15,7),'Weekly Calc'!$Q$5:$Q$15,0)),"") -> 4
B37: =IFERROR(INDEX('Weekly Calc'!$P$5:$P$15,MATCH(LARGE('Weekly Calc'!$Q$5:$Q$15,8),'Weekly Calc'!$Q$5:$Q$15,0)),"") -> Silk Pillowcase | C37: =IFERROR(LARGE('Weekly Calc'!$Q$5:$Q$15,8),"") -> 261 | D37: =IFERROR(INDEX('Weekly Calc'!$R$5:$R$15,MATCH(LARGE('Weekly Calc'!$Q$5:$Q$15,8),'Weekly Calc'!$Q$5:$Q$15,0)),"") -> 9
B40: What this report leaves out
B41: Stated rather than hidden, so the revenue figure above can be reconciled against the raw export.
B42: Refunds, this week | C42: =INDEX('Weekly Calc'!$L$5:$L$20,MATCH('Weekly Calc'!$H$3,'Weekly Calc'!$H$5:$H$20,0)) -> -386
B43: Shipping charged, all weeks | C43: =SUMIFS('Raw Orders'!$G$2:$G$1836,'Raw Orders'!$C$2:$C$1836,"Shipping") -> 2031.45
B44: Discounts given, all weeks | C44: =SUMIFS('Raw Orders'!$G$2:$G$1836,'Raw Orders'!$C$2:$C$1836,"Discount") -> -975
B45: Cancelled lines, all weeks | C45: =COUNTIFS('Raw Orders'!$K$2:$K$1836,"Cancelled") -> 36
B46: Product lines with no customer email | C46: =COUNTIFS('Raw Orders'!$J$2:$J$1836,"",'Raw Orders'!$C$2:$C$1836,"Product") -> 138
B49: Raw data in, report out, no manual steps. The Apps Script in this file emails this summary on a schedule.

Sheet Raw Orders
A1: Order ID | B1: Date | C1: Line Type | D1: Item | E1: Qty | F1: Unit Price | G1: Line Total | H1: Channel | I1: Country | J1: Customer Email | K1: Status
A2: #10017 | B2: 04/05/2026 07:04 | C2: Shipping | D2: Shipping | E2: 1 | F2: 3.95 | G2: 3.95 | H2: Website | I2: Germany | J2: customer650@example.com | K2: Fulfilled
A3: #10017 | B3: 2026-05-04 07:04 | C3: Discount | D3: Promo code | E3: 1 | F3: -10 | G3: -10 | H3: Website | I3: Germany | J3: customer650@example.com | K3: Fulfilled
A4: #10017 | B4: 2026-05-04 07:04 | C4: Product | D4: Fitted Sheet Single | E4: 1 | F4: 22 | G4: 22 | H4: Website | I4: Germany | J4: customer650@example.com | K4: Fulfilled
A5: #10017 | B5: 2026-05-04 07:04 | C5: Product | D5: Bamboo Pillow Pair | E5: 1 | F5: 39 | G5: 39 | H5: Website | I5: Germany | J5: customer650@example.com | K5: Fulfilled
A6: #10014 | B6: 2026-05-04 07:31 | C6: Product | D6: Cotton Waffle Throw | E6: 2 | F6: 45 | G6: 90 | H6: Instagram | I6: United Kingdom | J6: customer5@example.com | K6: Fulfilled
A7: #10014 | B7: 04/05/2026 07:31 | C7: Shipping | D7: Shipping | E7: 1 | F7: 5.95 | G7: 5.95 | H7: Instagram | I7: United Kingdom | J7: customer5@example.com | K7: Fulfilled
A8: #10003 | B8: 2026-05-04 08:36 | C8: Product | D8: Lavender Room Mist | E8: 1 | F8: 14 | G8: 14 | H8: Instagram | I8: United Kingdom | K8: Fulfilled
A9: #10003 | B9: 2026-05-04 08:36 | C9: Shipping | D9: Shipping | E9: 1 | F9: 4.95 | G9: 4.95 | H9: Instagram | I9: United Kingdom | K9: Fulfilled
A10: #10020 | B10: 2026-05-04 09:44 | C10: Product | D10: Storage Basket Large | E10: 3 | F10: 32 | G10: 96 | H10: Website | I10: United Kingdom | J10: customer172@example.com | K10: Fulfilled
A11: #10020 | B11: 2026-05-04 09:44 | C11: Shipping | D11: Shipping | E11: 1 | F11: 4.95 | G11: 4.95 | H11: Website | I11: United Kingdom | J11: customer172@example.com | K11: Fulfilled
A12: #10020 | B12: 04/05/2026 09:44 | C12: Product | D12: Silk Pillowcase | E12: 1 | F12: 29 | G12: 29 | H12: Website | I12: United Kingdom | J12: customer172@example.com | K12: Fulfilled
A13: #10020 | B13: 2026-05-04 09:44 | C13: Product | D13: Fitted Sheet Single | E13: 1 | F13: 22 | G13: 22 | H13: Website | I13: United Kingdom | J13: customer172@example.com | K13: Fulfilled
A14: #10034 | B14: 2026-05-04 13:53 | C14: Product | D14: Fitted Sheet Single | E14: 1 | F14: 22 | G14: 22 | H14: Website | I14: United Kingdom | J14: customer402@example.com | K14: Fulfilled
A15: #10034 | B15: 2026-05-04 13:53 | C15: Product | D15: Weighted Blanket 7kg | E15: 1 | F15: 55.2 | G15: 55.2 | H15: Website | I15: United Kingdom | J15: customer402@example.com | K15: Fulfilled
A16: #10034 | B16: 2026-05-04 13:53 | C16: Shipping | D16: Shipping | E16: 1 | F16: 5.95 | G16: 5.95 | H16: Website | I16: United Kingdom | J16: customer402@example.com | K16: Fulfilled
A17: #10034 | B17: 04/05/2026 13:53 | C17: Product | D17: Bamboo Pillow Pair | E17: 1 | F17: 39 | G17: 39 | H17: Website | I17: United Kingdom | J17: customer402@example.com | K17: Fulfilled
A18: #10046 | B18: 2026-05-04 16:44 | C18: Discount | D18: Promo code | E18: 1 | F18: -10 | G18: -10 | H18: Website | I18: United Kingdom | J18: customer853@example.com | K18: Fulfilled
A19: #10046 | B19: 2026-05-04 16:44 | C19: Product | D19: Linen Bedding Set | E19: 1 | F19: 89 | G19: 89 | H19: Website | I19: United Kingdom | J19: customer853@example.com | K19: Fulfilled
A20: #10023 | B20: 2026-05-04 18:05 | C20: Product | D20: Linen Bedding Set | E20: 1 | F20: 89 | G20: 89 | H20: Website | I20: United Kingdom | J20: customer202@example.com | K20: Fulfilled
A21: #10023 | B21: 2026-05-04 18:05 | C21: Shipping | D21: Shipping | E21: 1 | F21: 3.95 | G21: 3.95 | H21: Website | I21: United Kingdom | J21: customer202@example.com | K21: Fulfilled
... A39: #10048 | B39: 2026-05-05 19:55 | C39: Product | D39: Cotton Waffle Throw | E39: 1 | F39: 45 | G39: 45 | H39: Instagram | I39: France | J39: customer614@example.com | K39: Fulfilled
A40: #10037 | B40: 2026-05-05 20:12 | C40: Product | D40: Mattress Protector | E40: 1 | F40: 35 | G40: 35 | H40: Website | I40: United Kingdom | K40: Fulfilled
A41: #10037 | B41: 2026-05-05 20:12 | C41: Shipping | D41: Shipping | E41: 1 | F41: 0 | G41: 0 | H41: Website | I41: United Kingdom | K41: Fulfilled
A42: #10031 | B42: 06/05/2026 11:11 | C42: Product | D42: Cotton Waffle Throw | E42: 1 | F42: 45 | G42: 45 | H42: Website | I42: United Kingdom | J42: customer124@example.com | K42: Fulfilled
A43: #10031 | B43: 2026-05-06 11:11 | C43: Shipping | D43: Shipping | E43: 1 | F43: 0 | G43: 0 | H43: Website | I43: United Kingdom | J43: customer124@example.com | K43: Fulfilled
A44: #10030 | B44: 2026-05-06 11:34 | C44: Shipping | D44: Shipping | E44: 1 | F44: 3.95 | G44: 3.95 | H44: Website | I44: United Kingdom | J44: customer894@example.com | K44: Fulfilled
A45: #10004 | B45: 2026-05-06 11:34 | C45: Shipping | D45: Shipping | E45: 1 | F45: 4.95 | G45: 4.95 | H45: Website | I45: Ireland | J45: customer836@example.com | K45: Fulfilled
A46: #10004 | B46: 2026-05-06 11:34 | C46: Product | D46: Storage Basket Large | E46: 1 | F46: 32 | G46: 32 | H46: Website | I46: Ireland | J46: customer836@example.com | K46: Fulfilled
A47: #10004 | B47: 06/05/2026 11:34 | C47: Product | D47: Silk Pillowcase | E47: 1 | F47: 29 | G47: 29 | H47: Website | I47: Ireland | J47: customer836@example.com | K47: Fulfilled
A48: #10030 | B48: 2026-05-06 11:34 | C48: Product | D48: Lavender Room Mist | E48: 2 | F48: 14 | G48: 28 | H48: Website | I48: United Kingdom | J48: customer894@example.com | K48: Fulfilled
A49: #10053 | B49: 2026-05-06 11:58 | C49: Product | D49: Mattress Protector | E49: 1 | F49: 35 | G49: 35 | H49: Instagram | I49: Spain | J49: customer855@example.com | K49: Fulfilled
A50: #10053 | B50: 2026-05-06 11:58 | C50: Product | D50: Duvet Inner 10.5 tog | E50: 3 | F50: 67.5 | G50: 202.5 | H50: Instagram | I50: Spain | J50: customer855@example.com | K50: Fulfilled
A51: #10053 | B51: 2026-05-06 11:58 | C51: Shipping | D51: Shipping | E51: 1 | F51: 4.95 | G51: 4.95 | H51: Instagram | I51: Spain | J51: customer855@example.com | K51: Fulfilled
A52: #10053 | B52: 06/05/2026 11:58 | C52: Discount | D52: Promo code | E52: 1 | F52: -5 | G52: -5 | H52: Instagram | I52: Spain | J52: customer855@example.com | K52: Fulfilled
A53: #10050 | B53: 2026-05-06 13:15 | C53: Product | D53: Cotton Waffle Throw | E53: 1 | F53: 45 | G53: 45 | H53: Instagram | I53: Spain | K53: Fulfilled
A54: #10050 | B54: 2026-05-06 13:15 | C54: Shipping | D54: Shipping | E54: 1 | F54: 0 | G54: 0 | H54: Instagram | I54: Spain | K54: Fulfilled
A55: #10050 | B55: 2026-05-06 13:15 | C55: Discount | D55: Promo code | E55: 1 | F55: -10 | G55: -10 | H55: Instagram | I55: Spain | K55: Fulfilled
A56: #10050 | B56: 2026-05-06 13:15 | C56: Product | D56: Linen Bedding Set | E56: 2 | F56: 75.65 | G56: 151.3 | H56: Instagram | I56: Spain | K56: Fulfilled
A57: #10021 | B57: 06/05/2026 13:51 | C57: Product | D57: Mattress Protector | E57: 1 | F57: 35 | G57: 35 | H57: Website | I57: United Kingdom | J57: customer233@example.com | K57: Fulfilled
A58: #10021 | B58: 2026-05-06 13:51 | C58: Product | D58: Silk Pillowcase | E58: 1 | F58: 29 | G58: 29 | H58: Website | I58: United Kingdom | J58: customer233@example.com | K58: Fulfilled
A59: #10021 | B59: 2026-05-06 13:51 | C59: Product | D59: Fitted Sheet Single | E59: 1 | F59: 22 | G59: 22 | H59: Website | I59: United Kingdom | J59: customer233@example.com | K59: Fulfilled
A60: #10040 | B60: 2026-05-06 15:25 | C60: Shipping | D60: Shipping | E60: 1 | F60: 4.95 | G60: 4.95 | H60: Website | I60: United Kingdom | J60: customer585@example.com | K60: Fulfilled
A61: #10040 | B61: 2026-05-06 15:25 | C61: Product | D61: Bamboo Pillow Pair | E61: 2 | F61: 39 | G61: 78 | H61: Website | I61: United Kingdom | J61: customer585@example.com | K61: Fulfilled
A62: #10040 | B62: 06/05/2026 15:25 | C62: Product | D62: Silk Pillowcase | E62: 1 | F62: 29 | G62: 29 | H62: Website | I62: United Kingdom | J62: customer585@example.com | K62: Fulfilled
A63: #10013 | B63: 2026-05-06 15:45 | C63: Shipping | D63: Shipping | E63: 1 | F63: 4.95 | G63: 4.95 | H63: Website | I63: United Kingdom | J63: customer390@example.com | K63: Fulfilled
A64: #10013 | B64: 2026-05-06 15:45 | C64: Product | D64: Bamboo Pillow Pair | E64: 1 | F64: 39 | G64: 39 | H64: Website | I64: United Kingdom | J64: customer390@example.com | K64: Fulfilled
A65: #10013 | B65: 2026-05-06 15:45 | C65: Product | D65: Linen Bedding Set | E65: 1 | F65: 89 | G65: 89 | H65: Website | I65: United Kingdom | J65: customer390@example.com | K65: Fulfilled
A66: #10007 | B66: 2026-05-06 17:46 | C66: Product | D66: Linen Napkin Set of 4 | E66: 2 | F66: 26 | G66: 52 | H66: Website | I66: United Kingdom | J66: customer75@example.com | K66: Fulfilled
A67: #10007 | B67: 06/05/2026 17:46 | C67: Shipping | D67: Shipping | E67: 1 | F67: 5.95 | G67: 5.95 | H67: Website | I67: United Kingdom | J67: customer75@example.com | K67: Fulfilled
A68: #10011 | B68: 2026-05-06 19:56 | C68: Product | D68: Cotton Waffle Throw | E68: 1 | F68: 45 | G68: 45 | H68: Etsy | I68: United Kingdom | K68: Fulfilled
A69: #10011 | B69: 2026-05-06 19:56 | C69: Product | D69: Linen Bedding Set | E69: 2 | F69: 89 | G69: 178 | H69: Etsy | I69: United Kingdom | K69: Fulfilled
A70: #10011 | B70: 2026-05-06 19:56 | C70: Shipping | D70: Shipping | E70: 1 | F70: 3.95 | G70: 3.95 | H70: Etsy | I70: United Kingdom | K70: Fulfilled
A71: #10042 | B71: 2026-05-06 21:00 | C71: Shipping | D71: Shipping | E71: 1 | F71: 3.95 | G71: 3.95 | H71: Website | I71: Ireland | J71: customer275@example.com | K71: Fulfilled
A72: #10042 | B72: 06/05/2026 21:00 | C72: Product | D72: Linen Napkin Set of 4 | E72: 1 | F72: 26 | G72: 26 | H72: Website | I72: Ireland | J72: customer275@example.com | K72: Fulfilled
A73: #10042 | B73: 2026-05-06 21:00 | C73: Product | D73: Mattress Protector | E73: 1 | F73: 31.5 | G73: 31.5 | H73: Website | I73: Ireland | J73: customer275@example.com | K73: Fulfilled
A74: #10006 | B74: 2026-05-06 21:23 | C74: Product | D74: Cotton Waffle Throw | E74: 1 | F74: 45 | G74: 45 | H74: Website | I74: United Kingdom | J74: customer716@example.com | K74: Fulfilled
A75: #10006 | B75: 2026-05-06 21:23 | C75: Shipping | D75: Shipping | E75: 1 | F75: 5.95 | G75: 5.95 | H75: Website | I75: United Kingdom | J75: customer716@example.com | K75: Fulfilled
A76: #10055 | B76: 2026-05-07 07:29 | C76: Shipping | D76: Shipping | E76: 1 | F76: 3.95 | G76: 3.95 | H76: Website | I76: Netherlands | J76: customer549@example.com | K76: Fulfilled
A77: #10055 | B77: 07/05/2026 07:29 | C77: Product | D77: Linen Napkin Set of 4 | E77: 1 | F77: 26 | G77: 26 | H77: Website | I77: Netherlands | J77: customer549@example.com | K77: Fulfilled
A78: #10055 | B78: 2026-05-07 07:29 | C78: Product | D78: Weighted Blanket 7kg | E78: 1 | F78: 69 | G78: 69 | H78: Website | I78: Netherlands | J78: customer549@example.com | K78: Fulfilled
A79: #10055 | B79: 2026-05-07 07:29 | C79: Product | D79: Fitted Sheet Single | E79: 2 | F79: 22 | G79: 44 | H79: Website | I79: Netherlands | J79: customer549@example.com | K79: Fulfilled
A80: #10015 | B80: 2026-05-07 08:29 | C80: Product | D80: Fitted Sheet Single | E80: 2 | F80: 22 | G80: 44 | H80: Wholesale | I80: France | J80: customer402@example.com | K80: Fulfilled
A81: #10015 | B81: 2026-05-07 08:29 | C81: Shipping | D81: Shipping | E81: 1 | F81: 0 | G81: 0 | H81: Wholesale | I81: France | J81: customer402@example.com | K81: Fulfilled
A82: #10039 | B82: 07/05/2026 10:05 | C82: Shipping | D82: Shipping | E82: 1 | F82: 4.95 | G82: 4.95 | H82: Website | I82: United Kingdom | K82: Fulfilled
A83: #10039 | B83: 2026-05-07 10:05 | C83: Product | D83: Duvet Inner 10.5 tog | E83: 1 | F83: 75 | G83: 75 | H83: Website | I83: United Kingdom | K83: Fulfilled
A84: #10032 | B84: 2026-05-07 10:56 | C84: Shipping | D84: Shipping | E84: 1 | F84: 3.95 | G84: 3.95 | H84: Instagram | I84: United Kingdom | J84: customer284@example.com | K84: Fulfilled
A85: #10032 | B85: 2026-05-07 10:56 | C85: Product | D85: Mattress Protector | E85: 2 | F85: 28 | G85: 56 | H85: Instagram | I85: United Kingdom | J85: customer284@example.com | K85: Fulfilled
A86: #10032 | B86: 2026-05-07 10:56 | C86: Product | D86: Silk Pillowcase | E86: 3 | F86: 29 | G86: 87 | H86: Instagram | I86: United Kingdom | J86: customer284@example.com | K86: Fulfilled
A87: #10054 | B87: 07/05/2026 11:40 | C87: Product | D87: Duvet Inner 10.5 tog | E87: 1 | F87: 75 | G87: 75 | H87: Website | I87: United Kingdom | J87: customer463@example.com | K87: Fulfilled
A88: #10054 | B88: 2026-05-07 11:40 | C88: Shipping | D88: Shipping | E88: 1 | F88: 4.95 | G88: 4.95 | H88: Website | I88: United Kingdom | J88: customer463@example.com | K88: Fulfilled
A89: #10008 | B89: 2026-05-07 22:26 | C89: Product | D89: Cotton Waffle Throw | E89: 1 | F89: 45 | G89: 45 | H89: Website | I89: France | K89: Fulfilled
A90: #10025 | B90: 2026-05-07 22:56 | C90: Product | D90: Linen Napkin Set of 4 | E90: 2 | F90: 26 | G90: 52 | H90: Website | I90: United Kingdom | J90: customer341@example.com | K90: Fulfilled
A91: #10025 | B91: 2026-05-07 22:56 | C91: Product | D91: Linen Bedding Set | E91: 1 | F91: 80.1 | G91: 80.1 | H91: Website | I91: United Kingdom | J91: customer341@example.com | K91: Fulfilled
A92: #10025 | B92: 07/05/2026 22:56 | C92: Product | D92: Lavender Room Mist | E92: 1 | F92: 14 | G92: 14 | H92: Website | I92: United Kingdom | J92: customer341@example.com | K92: Fulfilled
A93: #10019 | B93: 2026-05-08 07:13 | C93: Product | D93: Weighted Blanket 7kg | E93: 1 | F93: 69 | G93: 69 | H93: Instagram | I93: United Kingdom | J93: customer557@example.com | K93: Fulfilled
A94: #10036 | B94: 2026-05-08 10:25 | C94: Product | D94: Fitted Sheet Single | E94: 2 | F94: 22 | G94: 44 | H94: Instagram | I94: United Kingdom | J94: customer853@example.com | K94: Fulfilled
A95: #10036 | B95: 2026-05-08 10:25 | C95: Product | D95: Weighted Blanket 7kg | E95: 1 | F95: 69 | G95: 69 | H95: Instagram | I95: United Kingdom | J95: customer853@example.com | K95: Fulfilled
A96: #10056 | B96: 2026-05-08 14:46 | C96: Shipping | D96: Shipping | E96: 1 | F96: 0 | G96: 0 | H96: Amazon | I96: United Kingdom | J96: customer666@example.com | K96: Fulfilled
A97: #10056 | B97: 08/05/2026 14:46 | C97: Product | D97: Linen Bedding Set | E97: 1 | F97: 89 | G97: 89 | H97: Amazon | I97: United Kingdom | J97: customer666@example.com | K97: Fulfilled
A98: #10056 | B98: 2026-05-08 14:46 | C98: Product | D98: Weighted Blanket 7kg | E98: 1 | F98: 69 | G98: 69 | H98: Amazon | I98: United Kingdom | J98: customer666@example.com | K98: Fulfilled
A99: #10045 | B99: 2026-05-08 14:59 | C99: Product | D99: Linen Bedding Set | E99: 1 | F99: 89 | G99: 89 | H99: Website | I99: United Kingdom | J99: customer666@example.com | K99: Fulfilled
A100: #10045 | B100: 2026-05-08 14:59 | C100: Shipping | D100: Shipping | E100: 1 | F100: 0 | G100: 0 | H100: Website | I100: United Kingdom | J100: customer666@example.com | K100: Fulfilled
A101: #10012 | B101: 2026-05-08 16:08 | C101: Shipping | D101: Shipping | E101: 1 | F101: 4.95 | G101: 4.95 | H101: Amazon | I101: United Kingdom | J101: customer893@example.com | K101: Fulfilled
... A108: #10029 | B108: 2026-05-08 20:53 | C108: Product | D108: Weighted Blanket 7kg | E108: 1 | F108: 69 | G108: 69 | H108: Website | I108: United Kingdom | J108: customer363@example.com | K108: Fulfilled
A109: #10018 | B109: 2026-05-08 21:30 | C109: Product | D109: Cotton Waffle Throw | E109: 1 | F109: 45 | G109: 45 | H109: Website | I109: United Kingdom | K109: Fulfilled
A110: #10018 | B110: 2026-05-08 21:30 | C110: Product | D110: Mattress Protector | E110: 1 | F110: 35 | G110: 35 | H110: Website | I110: United Kingdom | K110: Fulfilled
A111: #10018 | B111: 2026-05-08 21:30 | C111: Product | D111: Linen Bedding Set | E111: 3 | F111: 89 | G111: 267 | H111: Website | I111: United Kingdom | K111: Fulfilled
A112: #10038 | B112: 09/05/2026 07:24 | C112: Product | D112: Lavender Room Mist | E112: 2 | F112: 14 | G112: 28 | H112: Website | I112: United Kingdom | J112: customer525@example.com | K112: Fulfilled
A113: #10038 | B113: 2026-05-09 07:24 | C113: Shipping | D113: Shipping | E113: 1 | F113: 4.95 | G113: 4.95 | H113: Website | I113: United Kingdom | J113: customer525@example.com | K113: Fulfilled
A114: #10016 | B114: 2026-05-09 08:12 | C114: Product | D114: Linen Napkin Set of 4 | E114: 1 | F114: 26 | G114: 26 | H114: Website | I114: United Kingdom | J114: customer113@example.com | K114: Fulfilled
A115: #10016 | B115: 2026-05-09 08:12 | C115: Shipping | D115: Shipping | E115: 1 | F115: 3.95 | G115: 3.95 | H115: Website | I115: United Kingdom | J115: customer113@example.com | K115: Fulfilled
A116: #10016 | B116: 2026-05-09 08:12 | C116: Product | D116: Weighted Blanket 7kg | E116: 2 | F116: 55.2 | G116: 110.4 | H116: Website | I116: United Kingdom | J116: customer113@example.com | K116: Fulfilled
A117: #10041 | B117: 09/05/2026 09:17 | C117: Product | D117: Linen Bedding Set | E117: 2 | F117: 89 | G117: 178 | H117: Website | I117: Germany | K117: Fulfilled
A118: #10041 | B118: 2026-05-09 09:17 | C118: Product | D118: Storage Basket Large | E118: 1 | F118: 32 | G118: 32 | H118: Website | I118: Germany | K118: Fulfilled
A119: #10041 | B119: 2026-05-09 09:17 | C119: Shipping | D119: Shipping | E119: 1 | F119: 5.95 | G119: 5.95 | H119: Website | I119: Germany | K119: Fulfilled
A120: #10035 | B120: 2026-05-09 11:45 | C120: Product | D120: Cotton Waffle Throw | E120: 1 | F120: 45 | G120: 45 | H120: Etsy | I120: Germany | J120: customer260@example.com | K120: Fulfilled
A121: #10026 | B121: 2026-05-09 12:08 | C121: Product | D121: Weighted Blanket 7kg | E121: 1 | F121: 69 | G121: 69 | H121: Website | I121: United Kingdom | J121: customer477@example.com | K121: Fulfilled
A122: #10026 | B122: 09/05/2026 12:08 | C122: Shipping | D122: Shipping | E122: 1 | F122: 0 | G122: 0 | H122: Website | I122: United Kingdom | J122: customer477@example.com | K122: Fulfilled
A123: #10051 | B123: 2026-05-09 14:05 | C123: Shipping | D123: Shipping | E123: 1 | F123: 0 | G123: 0 | H123: Instagram | I123: United Kingdom | J123: customer159@example.com | K123: Fulfilled
...

Sheet Weekly Calc
A1: Query layer | H1: Weekly summary | P1: Reporting week breakdown
A2: Every column here reads from Raw Orders. Nothing is typed by hand, so pasting a new export updates the report by itself. | H2: The report tab reads from this table. | P2: =TEXT($H$3,"d mmm yyyy") -> 3 Aug 2026
G3: REPORTING WEEK | H3: =SUMPRODUCT(MAX(($J$5:$J$20>0)*($H$5:$H$20))) -> 46237 | I3: last week with orders, not just the last date in the file
A4: Order date | B4: Week starting (Mon) | C4: Product revenue | D4: Counts as an order | E4: Units | F4: Refund value | H4: Week starting | I4: Revenue | J4: Orders | K4: Units | L4: Refunds | M4: Avg order value | N4: vs prior week | P4: Product | Q4: Revenue | R4: Units | T4: Channel | U4: Revenue
A5: =IF('Raw Orders'!B2="","",IF(MID('Raw Orders'!B2,5,1)="-",DATE(VALUE(LEFT('Raw Orders'!B2,4)),VALUE(MID('Raw Orders'!B2,6,2)),VALUE(MID('Raw Orders'!B2,9,2))),DATE(VALUE(MID('Raw Orders'!B2,7,4)),VALUE(MID('Raw Orders'!B2,4,2)),VALUE(LEFT('Raw Orders'!B2,2))))) -> 46146 | B5: =IF(A5="","",A5-WEEKDAY(A5,3)) -> 46146 | C5: =IF(OR('Raw Orders'!C2<>"Product",'Raw Orders'!K2="Cancelled"),0,'Raw Orders'!G2) -> 0 | D5: =IF(AND('Raw Orders'!C2="Product",'Raw Orders'!K2="Fulfilled",COUNTIFS('Raw Orders'!$A$2:$A2,'Raw Orders'!A2,'Raw Orders'!$C$2:$C2,"Product",'Raw Orders'!$K$2:$K2,"Fulfilled")=1),1,0) -> 0 | E5: =IF(AND('Raw Orders'!C2="Product",'Raw Orders'!K2="Fulfilled"),'Raw Orders'!E2,0) -> 0 | F5: =IF('Raw Orders'!K2="Refunded",'Raw Orders'!G2,0) -> 0 | H5: =MIN($B$5:$B$1839) -> 46146 | I5: =SUMIFS($C$5:$C$1839,$B$5:$B$1839,H5) -> 6169.5 | J5: =SUMIFS($D$5:$D$1839,$B$5:$B$1839,H5) -> 56 | K5: =SUMIFS($E$5:$E$1839,$B$5:$B$1839,H5) -> 130 | L5: =SUMIFS($F$5:$F$1839,$B$5:$B$1839,H5) -> -45 | M5: =IFERROR(I5/J5,0) -> 110.16964 | P5: Bamboo Pillow Pair | Q5: =SUMIFS($C$5:$C$1839,$B$5:$B$1839,$H$3,'Raw Orders'!$D$2:$D$1836,$P5) -> 702 | R5: =SUMIFS($E$5:$E$1839,$B$5:$B$1839,$H$3,'Raw Orders'!$D$2:$D$1836,$P5) -> 20 | T5: Amazon | U5: =SUMIFS($C$5:$C$1839,$B$5:$B$1839,$H$3,'Raw Orders'!$H$2:$H$1836,$T5) -> 779.15
A6: =IF('Raw Orders'!B3="","",IF(MID('Raw Orders'!B3,5,1)="-",DATE(VALUE(LEFT('Raw Orders'!B3,4)),VALUE(MID('Raw Orders'!B3,6,2)),VALUE(MID('Raw Orders'!B3,9,2))),DATE(VALUE(MID('Raw Orders'!B3,7,4)),VALUE(MID('Raw Orders'!B3,4,2)),VALUE(LEFT('Raw Orders'!B3,2))))) -> 46146 | B6: =IF(A6="","",A6-WEEKDAY(A6,3)) -> 46146 | C6: =IF(OR('Raw Orders'!C3<>"Product",'Raw Orders'!K3="Cancelled"),0,'Raw Orders'!G3) -> 0 | D6: =IF(AND('Raw Orders'!C3="Product",'Raw Orders'!K3="Fulfilled",COUNTIFS('Raw Orders'!$A$2:$A3,'Raw Orders'!A3,'Raw Orders'!$C$2:$C3,"Product",'Raw Orders'!$K$2:$K3,"Fulfilled")=1),1,0) -> 0 | E6: =IF(AND('Raw Orders'!C3="Product",'Raw Orders'!K3="Fulfilled"),'Raw Orders'!E3,0) -> 0 | F6: =IF('Raw Orders'!K3="Refunded",'Raw Orders'!G3,0) -> 0 | H6: =H5+7 -> 46153 | I6: =SUMIFS($C$5:$C$1839,$B$5:$B$1839,H6) -> 4203.05 | J6: =SUMIFS($D$5:$D$1839,$B$5:$B$1839,H6) -> 44 | K6: =SUMIFS($E$5:$E$1839,$B$5:$B$1839,H6) -> 90 | L6: =SUMIFS($F$5:$F$1839,$B$5:$B$1839,H6) -> -39 | M6: =IFERROR(I6/J6,0) -> 95.523864 | N6: =IFERROR(I6/I5-1,"") -> -0.31873734 | P6: Cotton Waffle Throw | Q6: =SUMIFS($C$5:$C$1839,$B$5:$B$1839,$H$3,'Raw Orders'!$D$2:$D$1836,$P6) -> 585 | R6: =SUMIFS($E$5:$E$1839,$B$5:$B$1839,$H$3,'Raw Orders'!$D$2:$D$1836,$P6) -> 14 | T6: Etsy | U6: =SUMIFS($C$5:$C$1839,$B$5:$B$1839,$H$3,'Raw Orders'!$H$2:$H$1836,$T6) -> 418
A7: =IF('Raw Orders'!B4="","",IF(MID('Raw Orders'!B4,5,1)="-",DATE(VALUE(LEFT('Raw Orders'!B4,4)),VALUE(MID('Raw Orders'!B4,6,2)),VALUE(MID('Raw Orders'!B4,9,2))),DATE(VALUE(MID('Raw Orders'!B4,7,4)),VALUE(MID('Raw Orders'!B4,4,2)),VALUE(LEFT('Raw Orders'!B4,2))))) -> 46146 | B7: =IF(A7="","",A7-WEEKDAY(A7,3)) -> 46146 | C7: =IF(OR('Raw Orders'!C4<>"Product",'Raw Orders'!K4="Cancelled"),0,'Raw Orders'!G4) -> 22 | D7: =IF(AND('Raw Orders'!C4="Product",'Raw Orders'!K4="Fulfilled",COUNTIFS('Raw Orders'!$A$2:$A4,'Raw Orders'!A4,'Raw Orders'!$C$2:$C4,"Product",'Raw Orders'!$K$2:$K4,"Fulfilled")=1),1,0) -> 1 | E7: =IF(AND('Raw Orders'!C4="Product",'Raw Orders'!K4="Fulfilled"),'Raw Orders'!E4,0) -> 1 | F7: =IF('Raw Orders'!K4="Refunded",'Raw Orders'!G4,0) -> 0 | H7: =H6+7 -> 46160 | I7: =SUMIFS($C$5:$C$1839,$B$5:$B$1839,H7) -> 3420.3 | J7: =SUMIFS($D$5:$D$1839,$B$5:$B$1839,H7) -> 38 | K7: =SUMIFS($E$5:$E$1839,$B$5:$B$1839,H7) -> 84 | L7: =SUMIFS($F$5:$F$1839,$B$5:$B$1839,H7) -> -142 | M7: =IFERROR(I7/J7,0) -> 90.007895 | N7: =IFERROR(I7/I6-1,"") -> -0.18623381 | P7: Duvet Inner 10.5 tog | Q7: =SUMIFS($C$5:$C$1839,$B$5:$B$1839,$H$3,'Raw Orders'!$D$2:$D$1836,$P7) -> 300 | R7: =SUMIFS($E$5:$E$1839,$B$5:$B$1839,$H$3,'Raw Orders'!$D$2:$D$1836,$P7) -> 4 | T7: Instagram | U7: =SUMIFS($C$5:$C$1839,$B$5:$B$1839,$H$3,'Raw Orders'!$H$2:$H$1836,$T7) -> 1169.1
A8: =IF('Raw Orders'!B5="","",IF(MID('Raw Orders'!B5,5,1)="-",DATE(VALUE(LEFT('Raw Orders'!B5,4)),VALUE(MID('Raw Orders'!B5,6,2)),VALUE(MID('Raw Orders'!B5,9,2))),DATE(VALUE(MID('Raw Orders'!B5,7,4)),VALUE(MID('Raw Orders'!B5,4,2)),VALUE(LEFT('Raw Orders'!B5,2))))) -> 46146 | B8: =IF(A8="","",A8-WEEKDAY(A8,3)) -> 46146 | C8: =IF(OR('Raw Orders'!C5<>"Product",'Raw Orders'!K5="Cancelled"),0,'Raw Orders'!G5) -> 39 | D8: =IF(AND('Raw Orders'!C5="Product",'Raw Orders'!K5="Fulfilled",COUNTIFS('Raw Orders'!$A$2:$A5,'Raw Orders'!A5,'Raw Orders'!$C$2:$C5,"Product",'Raw Orders'!$K$2:$K5,"Fulfilled")=1),1,0) -> 0 | E8: =IF(AND('Raw Orders'!C5="Product",'Raw Orders'!K5="Fulfilled"),'Raw Orders'!E5,0) -> 1 | F8: =IF('Raw Orders'!K5="Refunded",'Raw Orders'!G5,0) -> 0 | H8: =H7+7 -> 46167 | I8: =SUMIFS($C$5:$C$1839,$B$5:$B$1839,H8) -> 5843.8 | J8: =SUMIFS($D$5:$D$1839,$B$5:$B$1839,H8) -> 53 | K8: =SUMIFS($E$5:$E$1839,$B$5:$B$1839,H8) -> 116 | L8: =SUMIFS($F$5:$F$1839,$B$5:$B$1839,H8) -> -255 | M8: =IFERROR(I8/J8,0) -> 110.26038 | N8: =IFERROR(I8/I7-1,"") -> 0.70856358 | P8: Fitted Sheet Single | Q8: =SUMIFS($C$5:$C$1839,$B$5:$B$1839,$H$3,'Raw Orders'!$D$2:$D$1836,$P8) -> 326.7 | R8: =SUMIFS($E$5:$E$1839,$B$5:$B$1839,$H$3,'Raw Orders'!$D$2:$D$1836,$P8) -> 17 | T8: Website | U8: =SUMIFS($C$5:$C$1839,$B$5:$B$1839,$H$3,'Raw Orders'!$H$2:$H$1836,$T8) -> 4201.9
A9: =IF('Raw Orders'!B6="","",IF(MID('Raw Orders'!B6,5,1)="-",DATE(VALUE(LEFT('Raw Orders'!B6,4)),VALUE(MID('Raw Orders'!B6,6,2)),VALUE(MID('Raw Orders'!B6,9,2))),DATE(VALUE(MID('Raw Orders'!B6,7,4)),VALUE(MID('Raw Orders'!B6,4,2)),VALUE(LEFT('Raw Orders'!B6,2))))) -> 46146 | B9: =IF(A9="","",A9-WEEKDAY(A9,3)) -> 46146 | C9: =IF(OR('Raw Orders'!C6<>"Product",'Raw Orders'!K6="Cancelled"),0,'Raw Orders'!G6) -> 90 | D9: =IF(AND('Raw Orders'!C6="Product",'Raw Orders'!K6="Fulfilled",COUNTIFS('Raw Orders'!$A$2:$A6,'Raw Orders'!A6,'Raw Orders'!$C$2:$C6,"Product",'Raw Orders'!$K$2:$K6,"Fulfilled")=1),1,0) -> 1 | E9: =IF(AND('Raw Orders'!C6="Product",'Raw Orders'!K6="Fulfilled"),'Raw Orders'!E6,0) -> 2 | F9: =IF('Raw Orders'!K6="Refunded",'Raw Orders'!G6,0) -> 0 | H9: =H8+7 -> 46174 | I9: =SUMIFS($C$5:$C$1839,$B$5:$B$1839,H9) -> 4768 | J9: =SUMIFS($D$5:$D$1839,$B$5:$B$1839,H9) -> 58 | K9: =SUMIFS($E$5:$E$1839,$B$5:$B$1839,H9) -> 113 | L9: =SUMIFS($F$5:$F$1839,$B$5:$B$1839,H9) -> -143 | M9: =IFERROR(I9/J9,0) -> 82.206897 | N9: =IFERROR(I9/I8-1,"") -> -0.18409254 | P9: Lavender Room Mist | Q9: =SUMIFS($C$5:$C$1839,$B$5:$B$1839,$H$3,'Raw Orders'!$D$2:$D$1836,$P9) -> 39.9 | R9: =SUMIFS($E$5:$E$1839,$B$5:$B$1839,$H$3,'Raw Orders'!$D$2:$D$1836,$P9) -> 3 | T9: Wholesale | U9: =SUMIFS($C$5:$C$1839,$B$5:$B$1839,$H$3,'Raw Orders'!$H$2:$H$1836,$T9) -> 271.9
A10: =IF('Raw Orders'!B7="","",IF(MID('Raw Orders'!B7,5,1)="-",DATE(VALUE(LEFT('Raw Orders'!B7,4)),VALUE(MID('Raw Orders'!B7,6,2)),VALUE(MID('Raw Orders'!B7,9,2))),DATE(VALUE(MID('Raw Orders'!B7,7,4)),VALUE(MID('Raw Orders'!B7,4,2)),VALUE(LEFT('Raw Orders'!B7,2))))) -> 46146 | B10: =IF(A10="","",A10-WEEKDAY(A10,3)) -> 46146 | C10: =IF(OR('Raw Orders'!C7<>"Product",'Raw Orders'!K7="Cancelled"),0,'Raw Orders'!G7) -> 0 | D10: =IF(AND('Raw Orders'!C7="Product",'Raw Orders'!K7="Fulfilled",COUNTIFS('Raw Orders'!$A$2:$A7,'Raw Orders'!A7,'Raw Orders'!$C$2:$C7,"Product",'Raw Orders'!$K$2:$K7,"Fulfilled")=1),1,0) -> 0 | E10: =IF(AND('Raw Orders'!C7="Product",'Raw Orders'!K7="Fulfilled"),'Raw Orders'!E7,0) -> 0 | F10: =IF('Raw Orders'!K7="Refunded",'Raw Orders'!G7,0) -> 0 | H10: =H9+7 -> 46181 | I10: =SUMIFS($C$5:$C$1839,$B$5:$B$1839,H10) -> 4908.2 | J10: =SUMIFS($D$5:$D$1839,$B$5:$B$1839,H10) -> 54 | K10: =SUMIFS($E$5:$E$1839,$B$5:$B$1839,H10) -> 109 | L10: =SUMIFS($F$5:$F$1839,$B$5:$B$1839,H10) -> -112 | M10: =IFERROR(I10/J10,0) -> 90.892593 | N10: =IFERROR(I10/I9-1,"") -> 0.029404362 | P10: Linen Bedding Set | Q10: =SUMIFS($C$5:$C$1839,$B$5:$B$1839,$H$3,'Raw Orders'!$D$2:$D$1836,$P10) -> 2006.95 | R10: =SUMIFS($E$5:$E$1839,$B$5:$B$1839,$H$3,'Raw Orders'!$D$2:$D$1836,$P10) -> 24
A11: =IF('Raw Orders'!B8="","",IF(MID('Raw Orders'!B8,5,1)="-",DATE(VALUE(LEFT('Raw Orders'!B8,4)),VALUE(MID('Raw Orders'!B8,6,2)),VALUE(MID('Raw Orders'!B8,9,2))),DATE(VALUE(MID('Raw Orders'!B8,7,4)),VALUE(MID('Raw Orders'!B8,4,2)),VALUE(LEFT('Raw Orders'!B8,2))))) -> 46146 | B11: =IF(A11="","",A11-WEEKDAY(A11,3)) -> 46146 | C11: =IF(OR('Raw Orders'!C8<>"Product",'Raw Orders'!K8="Cancelled"),0,'Raw Orders'!G8) -> 14 | D11: =IF(AND('Raw Orders'!C8="Product",'Raw Orders'!K8="Fulfilled",COUNTIFS('Raw Orders'!$A$2:$A8,'Raw Orders'!A8,'Raw Orders'!$C$2:$C8,"Product",'Raw Orders'!$K$2:$K8,"Fulfilled")=1),1,0) -> 1 | E11: =IF(AND('Raw Orders'!C8="Product",'Raw Orders'!K8="Fulfilled"),'Raw Orders'!E8,0) -> 1 | F11: =IF('Raw Orders'!K8="Refunded",'Raw Orders'!G8,0) -> 0 | H11: =H10+7 -> 46188 | I11: =SUMIFS($C$5:$C$1839,$B$5:$B$1839,H11) -> 5063 | J11: =SUMIFS($D$5:$D$1839,$B$5:$B$1839,H11) -> 52 | K11: =SUMIFS($E$5:$E$1839,$B$5:$B$1839,H11) -> 103 | L11: =SUMIFS($F$5:$F$1839,$B$5:$B$1839,H11) -> -127 | M11: =IFERROR(I11/J11,0) -> 97.365385 | N11: =IFERROR(I11/I10-1,"") -> 0.031539057 | P11: Linen Napkin Set of 4 | Q11: =SUMIFS($C$5:$C$1839,$B$5:$B$1839,$H$3,'Raw Orders'!$D$2:$D$1836,$P11) -> 156 | R11: =SUMIFS($E$5:$E$1839,$B$5:$B$1839,$H$3,'Raw Orders'!$D$2:$D$1836,$P11) -> 7
A12: =IF('Raw Orders'!B9="","",IF(MID('Raw Orders'!B9,5,1)="-",DATE(VALUE(LEFT('Raw Orders'!B9,4)),VALUE(MID('Raw Orders'!B9,6,2)),VALUE(MID('Raw Orders'!B9,9,2))),DATE(VALUE(MID('Raw Orders'!B9,7,4)),VALUE(MID('Raw Orders'!B9,4,2)),VALUE(LEFT('Raw Orders'!B9,2))))) -> 46146 | B12: =IF(A12="","",A12-WEEKDAY(A12,3)) -> 46146 | C12: =IF(OR('Raw Orders'!C9<>"Product",'Raw Orders'!K9="Cancelled"),0,'Raw Orders'!G9) -> 0 | D12: =IF(AND('Raw Orders'!C9="Product",'Raw Orders'!K9="Fulfilled",COUNTIFS('Raw Orders'!$A$2:$A9,'Raw Orders'!A9,'Raw Orders'!$C$2:$C9,"Product",'Raw Orders'!$K$2:$K9,"Fulfilled")=1),1,0) -> 0 | E12: =IF(AND('Raw Orders'!C9="Product",'Raw Orders'!K9="Fulfilled"),'Raw Orders'!E9,0) -> 0 | F12: =IF('Raw Orders'!K9="Refunded",'Raw Orders'!G9,0) -> 0 | H12: =H11+7 -> 46195 | I12: =SUMIFS($C$5:$C$1839,$B$5:$B$1839,H12) -> 4877.55 | J12: =SUMIFS($D$5:$D$1839,$B$5:$B$1839,H12) -> 50 | K12: =SUMIFS($E$5:$E$1839,$B$5:$B$1839,H12) -> 105 | L12: =SUMIFS($F$5:$F$1839,$B$5:$B$1839,H12) -> -266 | M12: =IFERROR(I12/J12,0) -> 97.551 | N12: =IFERROR(I12/I11-1,"") -> -0.036628481 | P12: Mattress Protector | Q12: =SUMIFS($C$5:$C$1839,$B$5:$B$1839,$H$3,'Raw Orders'!$D$2:$D$1836,$P12) -> 619.5 | R12: =SUMIFS($E$5:$E$1839,$B$5:$B$1839,$H$3,'Raw Orders'!$D$2:$D$1836,$P12) -> 19
A13: =IF('Raw Orders'!B10="","",IF(MID('Raw Orders'!B10,5,1)="-",DATE(VALUE(LEFT('Raw Orders'!B10,4)),VALUE(MID('Raw Orders'!B10,6,2)),VALUE(MID('Raw Orders'!B10,9,2))),DATE(VALUE(MID('Raw Orders'!B10,7,4)),VALUE(MID('Raw Orders'!B10,4,2)),VALUE(LEFT('Raw Orders'!B10,2))))) -> 46146 | B13: =IF(A13="","",A13-WEEKDAY(A13,3)) -> 46146 | C13: =IF(OR('Raw Orders'!C10<>"Product",'Raw Orders'!K10="Cancelled"),0,'Raw Orders'!G10) -> 96 | D13: =IF(AND('Raw Orders'!C10="Product",'Raw Orders'!K10="Fulfilled",COUNTIFS('Raw Orders'!$A$2:$A10,'Raw Orders'!A10,'Raw Orders'!$C$2:$C10,"Product",'Raw Orders'!$K$2:$K10,"Fulfilled")=1),1,0) -> 1 | E13: =IF(AND('Raw Orders'!C10="Product",'Raw Orders'!K10="Fulfilled"),'Raw Orders'!E10,0) -> 3 | F13: =IF('Raw Orders'!K10="Refunded",'Raw Orders'!G10,0) -> 0 | H13: =H12+7 -> 46202 | I13: =SUMIFS($C$5:$C$1839,$B$5:$B$1839,H13) -> 5541.3 | J13: =SUMIFS($D$5:$D$1839,$B$5:$B$1839,H13) -> 55 | K13: =SUMIFS($E$5:$E$1839,$B$5:$B$1839,H13) -> 118 | L13: =SUMIFS($F$5:$F$1839,$B$5:$B$1839,H13) -> -180.15 | M13: =IFERROR(I13/J13,0) -> 100.75091 | N13: =IFERROR(I13/I12-1,"") -> 0.13608266 | P13: Silk Pillowcase | Q13: =SUMIFS($C$5:$C$1839,$B$5:$B$1839,$H$3,'Raw Orders'!$D$2:$D$1836,$P13) -> 261 | R13: =SUMIFS($E$5:$E$1839,$B$5:$B$1839,$H$3,'Raw Orders'!$D$2:$D$1836,$P13) -> 9
A14: =IF('Raw Orders'!B11="","",IF(MID('Raw Orders'!B11,5,1)="-",DATE(VALUE(LEFT('Raw Orders'!B11,4)),VALUE(MID('Raw Orders'!B11,6,2)),VALUE(MID('Raw Orders'!B11,9,2))),DATE(VALUE(MID('Raw Orders'!B11,7,4)),VALUE(MID('Raw Orders'!B11,4,2)),VALUE(LEFT('Raw Orders'!B11,2))))) -> 46146 | B14: =IF(A14="","",A14-WEEKDAY(A14,3)) -> 46146 | C14: =IF(OR('Raw Orders'!C11<>"Product",'Raw Orders'!K11="Cancelled"),0,'Raw Orders'!G11) -> 0 | D14: =IF(AND('Raw Orders'!C11="Product",'Raw Orders'!K11="Fulfilled",COUNTIFS('Raw Orders'!$A$2:$A11,'Raw Orders'!A11,'Raw Orders'!$C$2:$C11,"Product",'Raw Orders'!$K$2:$K11,"Fulfilled")=1),1,0) -> 0 | E14: =IF(AND('Raw Orders'!C11="Product",'Raw Orders'!K11="Fulfilled"),'Raw Orders'!E11,0) -> 0 | F14: =IF('Raw Orders'!K11="Refunded",'Raw Orders'!G11,0) -> 0 | H14: =H13+7 -> 46209 | I14: =SUMIFS($C$5:$C$1839,$B$5:$B$1839,H14) -> 5333.1 | J14: =SUMIFS($D$5:$D$1839,$B$5:$B$1839,H14) -> 46 | K14: =SUMIFS($E$5:$E$1839,$B$5:$B$1839,H14) -> 116 | L14: =SUMIFS($F$5:$F$1839,$B$5:$B$1839,H14) -> -64 | M14: =IFERROR(I14/J14,0) -> 115.93696 | N14: =IFERROR(I14/I13-1,"") -> -0.037572411 | P14: Storage Basket Large | Q14: =SUMIFS($C$5:$C$1839,$B$5:$B$1839,$H$3,'Raw Orders'!$D$2:$D$1836,$P14) -> 256 | R14: =SUMIFS($E$5:$E$1839,$B$5:$B$1839,$H$3,'Raw Orders'!$D$2:$D$1836,$P14) -> 8
A15: =IF('Raw Orders'!B12="","",IF(MID('Raw Orders'!B12,5,1)="-",DATE(VALUE(LEFT('Raw Orders'!B12,4)),VALUE(MID('Raw Orders'!B12,6,2)),VALUE(MID('Raw Orders'!B12,9,2))),DATE(VALUE(MID('Raw Orders'!B12,7,4)),VALUE(MID('Raw Orders'!B12,4,2)),VALUE(LEFT('Raw Orders'!B12,2))))) -> 46146 | B15: =IF(A15="","",A15-WEEKDAY(A15,3)) -> 46146 | C15: =IF(OR('Raw Orders'!C12<>"Product",'Raw Orders'!K12="Cancelled"),0,'Raw Orders'!G12) -> 29 | D15: =IF(AND('Raw Orders'!C12="Product",'Raw Orders'!K12="Fulfilled",COUNTIFS('Raw Orders'!$A$2:$A12,'Raw Orders'!A12,'Raw Orders'!$C$2:$C12,"Product",'Raw Orders'!$K$2:$K12,"Fulfilled")=1),1,0) -> 0 | E15: =IF(AND('Raw Orders'!C12="Product",'Raw Orders'!K12="Fulfilled"),'Raw Orders'!E12,0) -> 1 | F15: =IF('Raw Orders'!K12="Refunded",'Raw Orders'!G12,0) -> 0 | H15: =H14+7 -> 46216 | I15: =SUMIFS($C$5:$C$1839,$B$5:$B$1839,H15) -> 5796.8 | J15: =SUMIFS($D$5:$D$1839,$B$5:$B$1839,H15) -> 54 | K15: =SUMIFS($E$5:$E$1839,$B$5:$B$1839,H15) -> 113 | L15: =SUMIFS($F$5:$F$1839,$B$5:$B$1839,H15) -> -14 | M15: =IFERROR(I15/J15,0) -> 107.34815 | N15: =IFERROR(I15/I14-1,"") -> 0.086947554 | P15: Weighted Blanket 7kg | Q15: =SUMIFS($C$5:$C$1839,$B$5:$B$1839,$H$3,'Raw Orders'!$D$2:$D$1836,$P15) -> 1587 | R15: =SUMIFS($E$5:$E$1839,$B$5:$B$1839,$H$3,'Raw Orders'!$D$2:$D$1836,$P15) -> 24
A16: =IF('Raw Orders'!B13="","",IF(MID('Raw Orders'!B13,5,1)="-",DATE(VALUE(LEFT('Raw Orders'!B13,4)),VALUE(MID('Raw Orders'!B13,6,2)),VALUE(MID('Raw Orders'!B13,9,2))),DATE(VALUE(MID('Raw Orders'!B13,7,4)),VALUE(MID('Raw Orders'!B13,4,2)),VALUE(LEFT('Raw Orders'!B13,2))))) -> 46146 | B16: =IF(A16="","",A16-WEEKDAY(A16,3)) -> 46146 | C16: =IF(OR('Raw Orders'!C13<>"Product",'Raw Orders'!K13="Cancelled"),0,'Raw Orders'!G13) -> 22 | D16: =IF(AND('Raw Orders'!C13="Product",'Raw Orders'!K13="Fulfilled",COUNTIFS('Raw Orders'!$A$2:$A13,'Raw Orders'!A13,'Raw Orders'!$C$2:$C13,"Product",'Raw Orders'!$K$2:$K13,"Fulfilled")=1),1,0) -> 0 | E16: =IF(AND('Raw Orders'!C13="Product",'Raw Orders'!K13="Fulfilled"),'Raw Orders'!E13,0) -> 1 | F16: =IF('Raw Orders'!K13="Refunded",'Raw Orders'!G13,0) -> 0 | H16: =H15+7 -> 46223 | I16: =SUMIFS($C$5:$C$1839,$B$5:$B$1839,H16) -> 3991.3 | J16: =SUMIFS($D$5:$D$1839,$B$5:$B$1839,H16) -> 46 | K16: =SUMIFS($E$5:$E$1839,$B$5:$B$1839,H16) -> 89 | L16: =SUMIFS($F$5:$F$1839,$B$5:$B$1839,H16) -> -203 | M16: =IFERROR(I16/J16,0) -> 86.767391 | N16: =IFERROR(I16/I15-1,"") -> -0.31146495
A17: =IF('Raw Orders'!B14="","",IF(MID('Raw Orders'!B14,5,1)="-",DATE(VALUE(LEFT('Raw Orders'!B14,4)),VALUE(MID('Raw Orders'!B14,6,2)),VALUE(MID('Raw Orders'!B14,9,2))),DATE(VALUE(MID('Raw Orders'!B14,7,4)),VALUE(MID('Raw Orders'!B14,4,2)),VALUE(LEFT('Raw Orders'!B14,2))))) -> 46146 | B17: =IF(A17="","",A17-WEEKDAY(A17,3)) -> 46146 | C17: =IF(OR('Raw Orders'!C14<>"Product",'Raw Orders'!K14="Cancelled"),0,'Raw Orders'!G14) -> 22 | D17: =IF(AND('Raw Orders'!C14="Product",'Raw Orders'!K14="Fulfilled",COUNTIFS('Raw Orders'!$A$2:$A14,'Raw Orders'!A14,'Raw Orders'!$C$2:$C14,"Product",'Raw Orders'!$K$2:$K14,"Fulfilled")=1),1,0) -> 1 | E17: =IF(AND('Raw Orders'!C14="Product",'Raw Orders'!K14="Fulfilled"),'Raw Orders'!E14,0) -> 1 | F17: =IF('Raw Orders'!K14="Refunded",'Raw Orders'!G14,0) -> 0 | H17: =H16+7 -> 46230 | I17: =SUMIFS($C$5:$C$1839,$B$5:$B$1839,H17) -> 5212.1 | J17: =SUMIFS($D$5:$D$1839,$B$5:$B$1839,H17) -> 48 | K17: =SUMIFS($E$5:$E$1839,$B$5:$B$1839,H17) -> 111 | L17: =SUMIFS($F$5:$F$1839,$B$5:$B$1839,H17) -> -121 | M17: =IFERROR(I17/J17,0) -> 108.58542 | N17: =IFERROR(I17/I16-1,"") -> 0.30586526
A18: =IF('Raw Orders'!B15="","",IF(MID('Raw Orders'!B15,5,1)="-",DATE(VALUE(LEFT('Raw Orders'!B15,4)),VALUE(MID('Raw Orders'!B15,6,2)),VALUE(MID('Raw Orders'!B15,9,2))),DATE(VALUE(MID('Raw Orders'!B15,7,4)),VALUE(MID('Raw Orders'!B15,4,2)),VALUE(LEFT('Raw Orders'!B15,2))))) -> 46146 | B18: =IF(A18="","",A18-WEEKDAY(A18,3)) -> 46146 | C18: =IF(OR('Raw Orders'!C15<>"Product",'Raw Orders'!K15="Cancelled"),0,'Raw Orders'!G15) -> 55.2 | D18: =IF(AND('Raw Orders'!C15="Product",'Raw Orders'!K15="Fulfilled",COUNTIFS('Raw Orders'!$A$2:$A15,'Raw Orders'!A15,'Raw Orders'!$C$2:$C15,"Product",'Raw Orders'!$K$2:$K15,"Fulfilled")=1),1,0) -> 0 | E18: =IF(AND('Raw Orders'!C15="Product",'Raw Orders'!K15="Fulfilled"),'Raw Orders'!E15,0) -> 1 | F18: =IF('Raw Orders'!K15="Refunded",'Raw Orders'!G15,0) -> 0 | H18: =H17+7 -> 46237 | I18: =SUMIFS($C$5:$C$1839,$B$5:$B$1839,H18) -> 6840.05 | J18: =SUMIFS($D$5:$D$1839,$B$5:$B$1839,H18) -> 63 | K18: =SUMIFS($E$5:$E$1839,$B$5:$B$1839,H18) -> 149 | L18: =SUMIFS($F$5:$F$1839,$B$5:$B$1839,H18) -> -386 | M18: =IFERROR(I18/J18,0) -> 108.57222 | N18: =IFERROR(I18/I17-1,"") -> 0.31234052
A19: =IF('Raw Orders'!B16="","",IF(MID('Raw Orders'!B16,5,1)="-",DATE(VALUE(LEFT('Raw Orders'!B16,4)),VALUE(MID('Raw Orders'!B16,6,2)),VALUE(MID('Raw Orders'!B16,9,2))),DATE(VALUE(MID('Raw Orders'!B16,7,4)),VALUE(MID('Raw Orders'!B16,4,2)),VALUE(LEFT('Raw Orders'!B16,2))))) -> 46146 | B19: =IF(A19="","",A19-WEEKDAY(A19,3)) -> 46146 | C19: =IF(OR('Raw Orders'!C16<>"Product",'Raw Orders'!K16="Cancelled"),0,'Raw Orders'!G16) -> 0 | D19: =IF(AND('Raw Orders'!C16="Product",'Raw Orders'!K16="Fulfilled",COUNTIFS('Raw Orders'!$A$2:$A16,'Raw Orders'!A16,'Raw Orders'!$C$2:$C16,"Product",'Raw Orders'!$K$2:$K16,"Fulfilled")=1),1,0) -> 0 | E19: =IF(AND('Raw Orders'!C16="Product",'Raw Orders'!K16="Fulfilled"),'Raw Orders'!E16,0) -> 0 | F19: =IF('Raw Orders'!K16="Refunded",'Raw Orders'!G16,0) -> 0 | H19: =H18+7 -> 46244 | I19: =SUMIFS($C$5:$C$1839,$B$5:$B$1839,H19) -> -22 | J19: =SUMIFS($D$5:$D$1839,$B$5:$B$1839,H19) -> 0 | K19: =SUMIFS($E$5:$E$1839,$B$5:$B$1839,H19) -> 0 | L19: =SUMIFS($F$5:$F$1839,$B$5:$B$1839,H19) -> -22 | M19: =IFERROR(I19/J19,0) -> 0 | N19: =IFERROR(I19/I18-1,"") -> -1.0032164
A20: =IF('Raw Orders'!B17="","",IF(MID('Raw Orders'!B17,5,1)="-",DATE(VALUE(LEFT('Raw Orders'!B17,4)),VALUE(MID('Raw Orders'!B17,6,2)),VALUE(MID('Raw Orders'!B17,9,2))),DATE(VALUE(MID('Raw Orders'!B17,7,4)),VALUE(MID('Raw Orders'!B17,4,2)),VALUE(LEFT('Raw Orders'!B17,2))))) -> 46146 | B20: =IF(A20="","",A20-WEEKDAY(A20,3)) -> 46146 | C20: =IF(OR('Raw Orders'!C17<>"Product",'Raw Orders'!K17="Cancelled"),0,'Raw Orders'!G17) -> 39 | D20: =IF(AND('Raw Orders'!C17="Product",'Raw Orders'!K17="Fulfilled",COUNTIFS('Raw Orders'!$A$2:$A17,'Raw Orders'!A17,'Raw Orders'!$C$2:$C17,"Product",'Raw Orders'!$K$2:$K17,"Fulfilled")=1),1,0) -> 0 | E20: =IF(AND('Raw Orders'!C17="Product",'Raw Orders'!K17="Fulfilled"),'Raw Orders'!E17,0) -> 1 | F20: =IF('Raw Orders'!K17="Refunded",'Raw Orders'!G17,0) -> 0 | H20: =H19+7 -> 46251 | I20: =SUMIFS($C$5:$C$1839,$B$5:$B$1839,H20) -> 0 | J20: =SUMIFS($D$5:$D$1839,$B$5:$B$1839,H20) -> 0 | K20: =SUMIFS($E$5:$E$1839,$B$5:$B$1839,H20) -> 0 | L20: =SUMIFS($F$5:$F$1839,$B$5:$B$1839,H20) -> 0 | M20: =IFERROR(I20/J20,0) -> 0 | N20: =IFERROR(I20/I19-1,"") -> -1
A21: =IF('Raw Orders'!B18="","",IF(MID('Raw Orders'!B18,5,1)="-",DATE(VALUE(LEFT('Raw Orders'!B18,4)),VALUE(MID('Raw Orders'!B18,6,2)),VALUE(MID('Raw Orders'!B18,9,2))),DATE(VALUE(MID('Raw Orders'!B18,7,4)),VALUE(MID('Raw Orders'!B18,4,2)),VALUE(LEFT('Raw Orders'!B18,2))))) -> 46146 | B21: =IF(A21="","",A21-WEEKDAY(A21,3)) -> 46146 | C21: =IF(OR('Raw Orders'!C18<>"Product",'Raw Orders'!K18="Cancelled"),0,'Raw Orders'!G18) -> 0 | D21: =IF(AND('Raw Orders'!C18="Product",'Raw Orders'!K18="Fulfilled",COUNTIFS('Raw Orders'!$A$2:$A18,'Raw Orders'!A18,'Raw Orders'!$C$2:$C18,"Product",'Raw Orders'!$K$2:$K18,"Fulfilled")=1),1,0) -> 0 | E21: =IF(AND('Raw Orders'!C18="Product",'Raw Orders'!K18="Fulfilled"),'Raw Orders'!E18,0) -> 0 | F21: =IF('Raw Orders'!K18="Refunded",'Raw Orders'!G18,0) -> 0
A22: =IF('Raw Orders'!B19="","",IF(MID('Raw Orders'!B19,5,1)="-",DATE(VALUE(LEFT('Raw Orders'!B19,4)),VALUE(MID('Raw Orders'!B19,6,2)),VALUE(MID('Raw Orders'!B19,9,2))),DATE(VALUE(MID('Raw Orders'!B19,7,4)),VALUE(MID('Raw Orders'!B19,4,2)),VALUE(LEFT('Raw Orders'!B19,2))))) -> 46146 | B22: =IF(A22="","",A22-WEEKDAY(A22,3)) -> 46146 | C22: =IF(OR('Raw Orders'!C19<>"Product",'Raw Orders'!K19="Cancelled"),0,'Raw Orders'!G19) -> 89 | D22: =IF(AND('Raw Orders'!C19="Product",'Raw Orders'!K19="Fulfilled",COUNTIFS('Raw Orders'!$A$2:$A19,'Raw Orders'!A19,'Raw Orders'!$C$2:$C19,"Product",'Raw Orders'!$K$2:$K19,"Fulfilled")=1),1,0) -> 1 | E22: =IF(AND('Raw Orders'!C19="Product",'Raw Orders'!K19="Fulfilled"),'Raw Orders'!E19,0) -> 1 | F22: =IF('Raw Orders'!K19="Refunded",'Raw Orders'!G19,0) -> 0
A23: =IF('Raw Orders'!B20="","",IF(MID('Raw Orders'!B20,5,1)="-",DATE(VALUE(LEFT('Raw Orders'!B20,4)),VALUE(MID('Raw Orders'!B20,6,2)),VALUE(MID('Raw Orders'!B20,9,2))),DATE(VALUE(MID('Raw Orders'!B20,7,4)),VALUE(MID('Raw Orders'!B20,4,2)),VALUE(LEFT('Raw Orders'!B20,2))))) -> 46146 | B23: =IF(A23="","",A23-WEEKDAY(A23,3)) -> 46146 | C23: =IF(OR('Raw Orders'!C20<>"Product",'Raw Orders'!K20="Cancelled"),0,'Raw Orders'!G20) -> 89 | D23: =IF(AND('Raw Orders'!C20="Product",'Raw Orders'!K20="Fulfilled",COUNTIFS('Raw Orders'!$A$2:$A20,'Raw Orders'!A20,'Raw Orders'!$C$2:$C20,"Product",'Raw Orders'!$K$2:$K20,"Fulfilled")=1),1,0) -> 1 | E23: =IF(AND('Raw Orders'!C20="Product",'Raw Orders'!K20="Fulfilled"),'Raw Orders'!E20,0) -> 1 | F23: =IF('Raw Orders'!K20="Refunded",'Raw Orders'!G20,0) -> 0
A24: =IF('Raw Orders'!B21="","",IF(MID('Raw Orders'!B21,5,1)="-",DATE(VALUE(LEFT('Raw Orders'!B21,4)),VALUE(MID('Raw Orders'!B21,6,2)),VALUE(MID('Raw Orders'!B21,9,2))),DATE(VALUE(MID('Raw Orders'!B21,7,4)),VALUE(MID('Raw Orders'!B21,4,2)),VALUE(LEFT('Raw Orders'!B21,2))))) -> 46146 | B24: =IF(A24="","",A24-WEEKDAY(A24,3)) -> 46146 | C24: =IF(OR('Raw Orders'!C21<>"Product",'Raw Orders'!K21="Cancelled"),0,'Raw Orders'!G21) -> 0 | D24: =IF(AND('Raw Orders'!C21="Product",'Raw Orders'!K21="Fulfilled",COUNTIFS('Raw Orders'!$A$2:$A21,'Raw Orders'!A21,'Raw Orders'!$C$2:$C21,"Product",'Raw Orders'!$K$2:$K21,"Fulfilled")=1),1,0) -> 0 | E24: =IF(AND('Raw Orders'!C21="Product",'Raw Orders'!K21="Fulfilled"),'Raw Orders'!E21,0) -> 0 | F24: =IF('Raw Orders'!K21="Refunded",'Raw Orders'!G21,0) -> 0
A25: =IF('Raw Orders'!B22="","",IF(MID('Raw Orders'!B22,5,1)="-",DATE(VALUE(LEFT('Raw Orders'!B22,4)),VALUE(MID('Raw Orders'!B22,6,2)),VALUE(MID('Raw Orders'!B22,9,2))),DATE(VALUE(MID('Raw Orders'!B22,7,4)),VALUE(MID('Raw Orders'!B22,4,2)),VALUE(LEFT('Raw Orders'!B22,2))))) -> 46146 | B25: =IF(A25="","",A25-WEEKDAY(A25,3)) -> 46146 | C25: =IF(OR('Raw Orders'!C22<>"Product",'Raw Orders'!K22="Cancelled"),0,'Raw Orders'!G22) -> 89 | D25: =IF(AND('Raw Orders'!C22="Product",'Raw Orders'!K22="Fulfilled",COUNTIFS('Raw Orders'!$A$2:$A22,'Raw Orders'!A22,'Raw Orders'!$C$2:$C22,"Product",'Raw Orders'!$K$2:$K22,"Fulfilled")=1),1,0) -> 1 | E25: =IF(AND('Raw Orders'!C22="Product",'Raw Orders'!K22="Fulfilled"),'Raw Orders'!E22,0) -> 1 | F25: =IF('Raw Orders'!K22="Refunded",'Raw Orders'!G22,0) -> 0
A26: =IF('Raw Orders'!B23="","",IF(MID('Raw Orders'!B23,5,1)="-",DATE(VALUE(LEFT('Raw Orders'!B23,4)),VALUE(MID('Raw Orders'!B23,6,2)),VALUE(MID('Raw Orders'!B23,9,2))),DATE(VALUE(MID('Raw Orders'!B23,7,4)),VALUE(MID('Raw Orders'!B23,4,2)),VALUE(LEFT('Raw Orders'!B23,2))))) -> 46146 | B26: =IF(A26="","",A26-WEEKDAY(A26,3)) -> 46146 | C26: =IF(OR('Raw Orders'!C23<>"Product",'Raw Orders'!K23="Cancelled"),0,'Raw Orders'!G23) -> 35 | D26: =IF(AND('Raw Orders'!C23="Product",'Raw Orders'!K23="Fulfilled",COUNTIFS('Raw Orders'!$A$2:$A23,'Raw Orders'!A23,'Raw Orders'!$C$2:$C23,"Product",'Raw Orders'!$K$2:$K23,"Fulfilled")=1),1,0) -> 0 | E26: =IF(AND('Raw Orders'!C23="Product",'Raw Orders'!K23="Fulfilled"),'Raw Orders'!E23,0) -> 1 | F26: =IF('Raw Orders'!K23="Refunded",'Raw Orders'!G23,0) -> 0
A27: =IF('Raw Orders'!B24="","",IF(MID('Raw Orders'!B24,5,1)="-",DATE(VALUE(LEFT('Raw Orders'!B24,4)),VALUE(MID('Raw Orders'!B24,6,2)),VALUE(MID('Raw Orders'!B24,9,2))),DATE(VALUE(MID('Raw Orders'!B24,7,4)),VALUE(MID('Raw Orders'!B24,4,2)),VALUE(LEFT('Raw Orders'!B24,2))))) -> 46146 | B27: =IF(A27="","",A27-WEEKDAY(A27,3)) -> 46146 | C27: =IF(OR('Raw Orders'!C24<>"Product",'Raw Orders'!K24="Cancelled"),0,'Raw Orders'!G24) -> 0 | D27: =IF(AND('Raw Orders'!C24="Product",'Raw Orders'!K24="Fulfilled",COUNTIFS('Raw Orders'!$A$2:$A24,'Raw Orders'!A24,'Raw Orders'!$C$2:$C24,"Product",'Raw Orders'!$K$2:$K24,"Fulfilled")=1),1,0) -> 0 | E27: =IF(AND('Raw Orders'!C24="Product",'Raw Orders'!K24="Fulfilled"),'Raw Orders'!E24,0) -> 0 | F27: =IF('Raw Orders'!K24="Refunded",'Raw Orders'!G24,0) -> 0
A28: =IF('Raw Orders'!B25="","",IF(MID('Raw Orders'!B25,5,1)="-",DATE(VALUE(LEFT('Raw Orders'!B25,4)),VALUE(MID('Raw Orders'!B25,6,2)),VALUE(MID('Raw Orders'!B25,9,2))),DATE(VALUE(MID('Raw Orders'!B25,7,4)),VALUE(MID('Raw Orders'!B25,4,2)),VALUE(LEFT('Raw Orders'!B25,2))))) -> 46147 | B28: =IF(A28="","",A28-WEEKDAY(A28,3)) -> 46146 | C28: =IF(OR('Raw Orders'!C25<>"Product",'Raw Orders'!K25="Cancelled"),0,'Raw Orders'!G25) -> 0 | D28: =IF(AND('Raw Orders'!C25="Product",'Raw Orders'!K25="Fulfilled",COUNTIFS('Raw Orders'!$A$2:$A25,'Raw Orders'!A25,'Raw Orders'!$C$2:$C25,"Product",'Raw Orders'!$K$2:$K25,"Fulfilled")=1),1,0) -> 0 | E28: =IF(AND('Raw Orders'!C25="Product",'Raw Orders'!K25="Fulfilled"),'Raw Orders'!E25,0) -> 0 | F28: =IF('Raw Orders'!K25="Refunded",'Raw Orders'!G25,0) -> 0
A29: =IF('Raw Orders'!B26="","",IF(MID('Raw Orders'!B26,5,1)="-",DATE(VALUE(LEFT('Raw Orders'!B26,4)),VALUE(MID('Raw Orders'!B26,6,2)),VALUE(MID('Raw Orders'!B26,9,2))),DATE(VALUE(MID('Raw Orders'!B26,7,4)),VALUE(MID('Raw Orders'!B26,4,2)),VALUE(LEFT('Raw Orders'!B26,2))))) -> 46147 | B29: =IF(A29="","",A29-WEEKDAY(A29,3)) -> 46146 | C29: =IF(OR('Raw Orders'!C26<>"Product",'Raw Orders'!K26="Cancelled"),0,'Raw Orders'!G26) -> 70 | D29: =IF(AND('Raw Orders'!C26="Product",'Raw Orders'!K26="Fulfilled",COUNTIFS('Raw Orders'!$A$2:$A26,'Raw Orders'!A26,'Raw Orders'!$C$2:$C26,"Product",'Raw Orders'!$K$2:$K26,"Fulfilled")=1),1,0) -> 1 | E29: =IF(AND('Raw Orders'!C26="Product",'Raw Orders'!K26="Fulfilled"),'Raw Orders'!E26,0) -> 2 | F29: =IF('Raw Orders'!K26="Refunded",'Raw Orders'!G26,0) -> 0
A30: =IF('Raw Orders'!B27="","",IF(MID('Raw Orders'!B27,5,1)="-",DATE(VALUE(LEFT('Raw Orders'!B27,4)),VALUE(MID('Raw Orders'!B27,6,2)),VALUE(MID('Raw Orders'!B27,9,2))),DATE(VALUE(MID('Raw Orders'!B27,7,4)),VALUE(MID('Raw Orders'!B27,4,2)),VALUE(LEFT('Raw Orders'!B27,2))))) -> 46147 | B30: =IF(A30="","",A30-WEEKDAY(A30,3)) -> 46146 | C30: =IF(OR('Raw Orders'!C27<>"Product",'Raw Orders'!K27="Cancelled"),0,'Raw Orders'!G27) -> 70 | D30: =IF(AND('Raw Orders'!C27="Product",'Raw Orders'!K27="Fulfilled",COUNTIFS('Raw Orders'!$A$2:$A27,'Raw Orders'!A27,'Raw Orders'!$C$2:$C27,"Product",'Raw Orders'!$K$2:$K27,"Fulfilled")=1),1,0) -> 0 | E30: =IF(AND('Raw Orders'!C27="Product",'Raw Orders'!K27="Fulfilled"),'Raw Orders'!E27,0) -> 2 | F30: =IF('Raw Orders'!K27="Refunded",'Raw Orders'!G27,0) -> 0
A31: =IF('Raw Orders'!B28="","",IF(MID('Raw Orders'!B28,5,1)="-",DATE(VALUE(LEFT('Raw Orders'!B28,4)),VALUE(MID('Raw Orders'!B28,6,2)),VALUE(MID('Raw Orders'!B28,9,2))),DATE(VALUE(MID('Raw Orders'!B28,7,4)),VALUE(MID('Raw Orders'!B28,4,2)),VALUE(LEFT('Raw Orders'!B28,2))))) -> 46147 | B31: =IF(A31="","",A31-WEEKDAY(A31,3)) -> 46146 | C31: =IF(OR('Raw Orders'!C28<>"Product",'Raw Orders'!K28="Cancelled"),0,'Raw Orders'!G28) -> 0 | D31: =IF(AND('Raw Orders'!C28="Product",'Raw Orders'!K28="Fulfilled",COUNTIFS('Raw Orders'!$A$2:$A28,'Raw Orders'!A28,'Raw Orders'!$C$2:$C28,"Product",'Raw Orders'!$K$2:$K28,"Fulfilled")=1),1,0) -> 0 | E31: =IF(AND('Raw Orders'!C28="Product",'Raw Orders'!K28="Fulfilled"),'Raw Orders'!E28,0) -> 0 | F31: =IF('Raw Orders'!K28="Refunded",'Raw Orders'!G28,0) -> 0
A32: =IF('Raw Orders'!B29="","",IF(MID('Raw Orders'!B29,5,1)="-",DATE(VALUE(LEFT('Raw Orders'!B29,4)),VALUE(MID('Raw Orders'!B29,6,2)),VALUE(MID('Raw Orders'!B29,9,2))),DATE(VALUE(MID('Raw Orders'!B29,7,4)),VALUE(MID('Raw Orders'!B29,4,2)),VALUE(LEFT('Raw Orders'!B29,2))))) -> 46147 | B32: =IF(A32="","",A32-WEEKDAY(A32,3)) -> 46146 | C32: =IF(OR('Raw Orders'!C29<>"Product",'Raw Orders'!K29="Cancelled"),0,'Raw Orders'!G29) -> 105 | D32: =IF(AND('Raw Orders'!C29="Product",'Raw Orders'!K29="Fulfilled",COUNTIFS('Raw Orders'!$A$2:$A29,'Raw Orders'!A29,'Raw Orders'!$C$2:$C29,"Product",'Raw Orders'!$K$2:$K29,"Fulfilled")=1),1,0) -> 1 | E32: =IF(AND('Raw Orders'!C29="Product",'Raw Orders'!K29="Fulfilled"),'Raw Orders'!E29,0) -> 3 | F32: =IF('Raw Orders'!K29="Refunded",'Raw Orders'!G29,0) -> 0
... A1839: =IF('Raw Orders'!B1836="","",IF(MID('Raw Orders'!B1836,5,1)="-",DATE(VALUE(LEFT('Raw Orders'!B1836,4)),VALUE(MID('Raw Orders'!B1836,6,2)),VALUE(MID('Raw Orders'!B1836,9,2))),DATE(VALUE(MID('Raw Orders'!B1836,7,4)),VALUE(MID('Raw Orders'!B1836,4,2)),VALUE(LEFT('Raw Orders'!B1836,2))))) -> 46244 | B1839: =IF(A1839="","",A1839-WEEKDAY(A1839,3)) -> 46244 | C1839: =IF(OR('Raw Orders'!C1836<>"Product",'Raw Orders'!K1836="Cancelled"),0,'Raw Orders'!G1836) -> -22 | D1839: =IF(AND('Raw Orders'!C1836="Product",'Raw Orders'!K1836="Fulfilled",COUNTIFS('Raw Orders'!$A$2:$A1836,'Raw Orders'!A1836,'Raw Orders'!$C$2:$C1836,"Product",'Raw Orders'!$K$2:$K1836,"Fulfilled")=1),1,0) -> 0 | E1839: =IF(AND('Raw Orders'!C1836="Product",'Raw Orders'!K1836="Fulfilled"),'Raw Orders'!E1836,0) -> 0 | F1839: =IF('Raw Orders'!K1836="Refunded",'Raw Orders'!G1836,0) -> -22
